Workbook

Sheet Dashboard
B2: TechStore | Reporte ejecutivo de ventas y margen | L2: Actualizado: 06/08/2026 · Moneda: USD
B3: Ejercicios 2024-2025 · 2.400 operaciones depuradas · 5 regiones · 2 canales
B6: =Calculos!$B$85 -> Las ventas crecen 17.8% y el margen cae 2.4 p.p.: el costo de compra y la logistica del e-commerce se reparten el deterioro
B7: =Calculos!$B$86 -> El margen bruto pasa de 35.8% a 33.3%. La logistica explica 32% del mayor costo y el resto es precio de compra: son dos causas, no una.
B9: VENTAS 2025 | F9: MARGEN BRUTO | J9: CRECIMIENTO INTERANUAL | N9: COSTO LOGISTICO / VENTAS
B10: =Calculos!$B$17 -> 5566045.6 | F10: =Calculos!$B$18 -> 0.33303577 | J10: =Calculos!$B$19 -> 0.17767141 | N10: =Calculos!$B$20 -> 0.033020193
B12: ="vs meta "&TEXT(Calculos!$C$17,"$#,##0")&" "&TEXT(Calculos!$D$17,"+#,##0;-#,##0")&" USD" -> vs meta $5,400,000 +166,046 USD | F12: ="vs meta "&TEXT(Calculos!$C$18,"0.0%")&" "&TEXT(Calculos!$B$21,"+0.0;-0.0")&" p.p. vs 2024" -> vs meta 34.0% -2.4 p.p. vs 2024 | J12: ="vs meta "&TEXT(Calculos!$C$19,"0.0%")&" "&TEXT(Calculos!$D$19*100,"+0.0;-0.0")&" p.p." -> vs meta 15.0% +2.8 p.p. | N12: ="techo "&TEXT(Calculos!$C$20,"0.00%")&" "&TEXT(Calculos!$B$22,"+0.00;-0.00")&" p.p. vs 2024" -> techo 2.50% +1.13 p.p. vs 2024
B13: =Calculos!$D$17 -> 166045.6 | F13: =Calculos!$D$18 -> -0.006964225 | J13: =Calculos!$D$19 -> 0.027671414 | N13: =Calculos!$D$20 -> -0.008020193
B14: FILTROS · cualquier seleccion recalcula a la vez las cuatro tarjetas y los cinco graficos
B25: 1 · QUE PASO · evolucion de las ventas y del margen
B44: 2 · POR QUE · de donde sale la caida del margen
B63: 3 · DONDE ACTUAR · que productos miran primero
B82: =Calculos!$B$95 -> Zona de riesgo (margen por debajo de 33%): Laptop Pro 15, PC Gamer Ryzen. El resto de los productos esta en meta.
B84: REPORTE EJECUTIVO · cada linea dice primero el dato y despues que hacer con el
B85: =Calculos!$B$92 -> EVIDENCIA: las ventas suben 17.8% y las unidades 14.4%. INSIGHT: el crecimiento es de volumen, no de precio, asi que la demanda es real y conviene sostener el plan comercial.
B87: =Calculos!$B$93 -> EVIDENCIA: el costo de compra resta $172,502 y la logistica $80,921 de margen. INSIGHT: la caida tiene dos causas, no una; atribuirla solo al e-commerce sobreestima su peso y desviaria el presupuesto de correccion.
B89: =Calculos!$B$94 -> EVIDENCIA: el segundo semestre (34.5%) supera al primero (31.8%) pero sigue por debajo del mismo periodo de 2024 (35.7%). INSIGHT: la correccion del Q3 funciona pero es parcial; hay que sostenerla en el proximo semestre antes de fijar nuevas metas.
B92: Fuente: export del sistema transaccional depurado en este mismo libro (hojas Datos_Origen -> Datos_Limpios -> Control_Calidad). Metas y supuestos en la hoja Parametros. Dataset simulado con fines academicos. Elaborado por Lleyton Murphy · Coderhouse, Data Analyst · Practica Integradora Final.

Sheet Tablas_Dinamicas
B2: Tablas dinamicas del reporte | L2: Como leer esta hoja
B3: Las cuatro resumen la tabla de hechos depurada y comparten el mismo cache: los segmentadores del tablero las filtran a todas a la vez. Los graficos del dashboard leen exactamente estos numeros.
L4: Las cuatro tablas salen del mismo cache de datos, asi que los cuatro segmentadores del tablero (Trimestre, Categoria, Region y Canal) las filtran simultaneamente.
B5: 1 · Ventas, margen y unidades por REGION | G5: 2 · Ventas, margen y unidades por CATEGORIA
C6: Valores | H6: Valores
B7: Region | C7: Ventas | D7: Margen | E7: Unidades | G7: Categoria | H7: Ventas | I7: Margen | J7: Unidades
B8: AMBA | C8: 3896685.1 | D8: 1341318.3 | E8: 20839 | G8: Computacion | H8: 6696685.1 | I8: 2025842.5 | J8: 6213
B9: Centro | C9: 2262766.3 | D9: 780708.6 | E9: 12174 | G9: Accesorios | H9: 1798331.7 | I9: 797730.33 | J9: 28941 | L9: La tabla 4 resume una columna que no existe en el origen: Segmento_Rentabilidad se calcula con SI/Y/O en Datos_Limpios contra los umbrales de Parametros.
B10: Litoral | C10: 1655093.7 | D10: 569389.84 | E10: 8826 | G10: Audio | H10: 883546.05 | I10: 365080.4 | J10: 8706
B11: Cuyo | C11: 1247848.4 | D11: 427843.83 | E11: 6595 | G11: Almacenamiento | H11: 913797.32 | I11: 354857.8 | J11: 11200
B12: NOA | C12: 1229966.7 | D12: 424250.41 | E12: 6626 | G12: Total general | H12: 10292360 | I12: 3543511 | J12: 55060
B13: Total general | C13: 10292360 | D13: 3543511 | E13: 55060
L14: Si los numeros no se mueven al abrir el archivo: Datos > Actualizar todo. El libro pide el refresco al abrir, pero algunos visores de terceros no ejecutan tablas dinamicas.
B15: 3 · Ventas, margen y unidades por PRODUCTO | G15: 4 · Ventas y unidades por SEGMENTO DE RENTABILIDAD (columna calculada con SI/Y/O)
C16: Valores | H16: Valores
B17: Producto | C17: Ventas | D17: Margen | E17: Unidades | G17: Segmento_Rentabilidad | H17: Ventas | I17: Unidades
B18: Laptop Pro 15 | C18: 2453170.1 | D18: 813067.5 | E18: 2080 | G18: Alta rentabilidad | H18: 3436432.4 | I18: 21127
B19: Monitor 4K 27 | C19: 922212.2 | D19: 319601.57 | E19: 2085 | G19: Estandar | H19: 4927827.4 | I19: 32390
B20: PC Gamer Ryzen | C20: 3321302.8 | D20: 893173.42 | E20: 2048 | G20: Revisar | H20: 1928100.4 | I20: 1543
B21: Mouse Inalambrico | C21: 266495.76 | D21: 127912.83 | E21: 9612 | G21: Total general | H21: 10292360 | I21: 55060
B22: Teclado Mecanico | C22: 911123.2 | D22: 413486.14 | E22: 9685
B23: Webcam Full HD | C23: 620712.72 | D23: 256331.36 | E23: 9644
B24: Auriculares BT Pro | C24: 516529.41 | D24: 221197.49 | E24: 4346
B25: Parlante Bluetooth | C25: 367016.64 | D25: 143882.91 | E25: 4360
B26: SSD Externo 1TB | C26: 719241.26 | D26: 267534.87 | E26: 5587
B27: Pendrive 256GB | C27: 194556.06 | D27: 87322.93 | E27: 5613
B28: Total general | C28: 10292360 | D28: 3543511 | E28: 55060
B31: CONSULTA PUNTUAL · elegi los valores en las listas desplegables
B32: Complementa a las tablas dinamicas: responde una pregunta concreta sin tocar los filtros del tablero. Las tres celdas azules son listas de validacion; el resto son formulas SUMAR.SI.CONJUNTO sobre Datos_Limpios.
B35: Region | C35: AMBA | D35: Ventas | E35: =SUMIFS(Datos_Limpios!$R$2:$R$2401,Datos_Limpios!$H$2:$H$2401,$C$35,Datos_Limpios!$K$2:$K$2401,$C$36,Datos_Limpios!$C$2:$C$2401,$F$35) -> 2537006.1 | F35: =IF($C$37="Todos",">0","="&$C$37) -> >0
B36: Categoria | C36: Computacion | D36: Margen bruto | E36: =SUMIFS(Datos_Limpios!$U$2:$U$2401,Datos_Limpios!$H$2:$H$2401,$C$35,Datos_Limpios!$K$2:$K$2401,$C$36,Datos_Limpios!$C$2:$C$2401,$F$35) -> 767191.43
B37: Anio | C37: Todos | D37: Unidades | E37: =SUMIFS(Datos_Limpios!$O$2:$O$2401,Datos_Limpios!$H$2:$H$2401,$C$35,Datos_Limpios!$K$2:$K$2401,$C$36,Datos_Limpios!$C$2:$C$2401,$F$35) -> 2366
D38: Margen bruto % | E38: =IFERROR(E36/E35,0) -> 0.30240031
D39: Operaciones | E39: =COUNTIFS(Datos_Limpios!$H$2:$H$2401,$C$35,Datos_Limpios!$K$2:$K$2401,$C$36,Datos_Limpios!$C$2:$C$2401,$F$35) -> 144
B41: Nota: la opcion "Todos" del anio se resuelve con un criterio dinamico (">0") en la celda tecnica F35, para que una misma formula sirva para un anio puntual y para el total.

Sheet Datos_Limpios
A1: ID_Venta | B1: Fecha | C1: Anio | D1: Trimestre | E1: Mes_Num | F1: Mes | G1: Periodo | H1: Region | I1: Ciudad | J1: Canal | K1: Categoria | L1: Cat_Anio | M1: Producto | N1: Prod_Anio | O1: Unidades | P1: Precio_Unitario | Q1: Costo_Unitario | R1: Ventas | S1: Costo_Producto | T1: Costo_Logistico | U1: Margen_Bruto | V1: Margen_Pct | W1: Segmento_Rentabilidad | X1: Alerta_Logistica | Y1: Ticket | Z1: Pos_Origen | AA1: Control_ETL | AB1: Fecha_Origen | AC1: Unidades_Origen | AD1: Ciudad_Origen
A2: =INDEX(Datos_Origen!$A$2:$A$2459,$Z2) -> 1 | B2: =IF(ISNUMBER($AB2),$AB2,IF(MID($AB2,5,1)="-",DATE(VALUE(LEFT($AB2,4)),VALUE(MID($AB2,6,2)),VALUE(RIGHT($AB2,2))),DATE(VALUE(RIGHT($AB2,4)),VALUE(MID($AB2,4,2)),VALUE(LEFT($AB2,2))))) -> 45299 | C2: =YEAR($B2) -> 2024 | D2: ="Q"&ROUNDUP(MONTH($B2)/3,0) -> Q1 | E2: =MONTH($B2) -> 1 | F2: =INDEX(Parametros!$I$5:$I$16,$E2) -> Ene | G2: =TEXT($C2,"0000")&"-"&TEXT($E2,"00") -> 2024-01 | H2: =INDEX(Parametros!$C$71:$C$91,MATCH(TRIM(INDEX(Datos_Origen!$C$2:$C$2459,$Z2)),Parametros!$B$71:$B$91,0)) -> AMBA | I2: =IF(TRIM($AD2)="",INDEX(Parametros!$I$20:$I$24,MATCH($H2,Parametros!$H$20:$H$24,0)),TRIM($AD2)) -> Buenos Aires | J2: =INDEX(Parametros!$C$95:$C$106,MATCH(TRIM(INDEX(Datos_Origen!$E$2:$E$2459,$Z2)),Parametros!$B$95:$B$106,0)) -> Tienda fisica | K2: =INDEX(Parametros!$C$48:$C$67,MATCH(TRIM(INDEX(Datos_Origen!$F$2:$F$2459,$Z2)),Parametros!$B$48:$B$67,0)) -> Computacion | L2: =$K2&" "&$C2 -> Computacion 2024 | M2: =TRIM(INDEX(Datos_Origen!$G$2:$G$2459,$Z2)) -> Laptop Pro 15 | N2: =$M2&" "&$C2 -> Laptop Pro 15 2024 | O2: =IF(ISTEXT($AC2),VALUE($AC2),$AC2) -> 21 | P2: =INDEX(Datos_Origen!$I$2:$I$2459,$Z2) -> 1176 | Q2: =INDEX(Datos_Origen!$J$2:$J$2459,$Z2) -> 744 | R2: =ROUND($O2*$P2,2) -> 24696 | S2: =ROUND($O2*$Q2,2) -> 15624 | T2: =ROUND($R2*SUMIFS(Parametros!$E$28:$E$43,Parametros!$B$28:$B$43,$J2,Parametros!$C$28:$C$43,$C2,Parametros!$D$28:$D$43,$D2),2) -> 296.35 | U2: =$R2-$S2-$T2 -> 8775.65 | V2: =IFERROR($U2/$R2,0) -> 0.35534702 | W2: =IF(AND($V2>=Parametros!$C$8,$R2>=Parametros!$C$12),"Alta rentabilidad",IF(OR($V2<Parametros!$C$11,$R2<Parametros!$C$13),"Revisar","Estandar")) -> Alta rentabilidad | X2: =IF(AND($J2="E-commerce",IFERROR($T2/$R2,0)>Parametros!$C$14),"Alerta","OK") -> OK | Y2: =IF($R2>=Parametros!$C$12,"Alto",IF($R2<Parametros!$C$13,"Bajo","Medio")) -> Alto | Z2: 2024 | AA2: =IF(MATCH($A2,Datos_Origen!$A$2:$A$2459,0)=$Z2,"OK","REVISAR") -> OK | AB2: =INDEX(Datos_Origen!$B$2:$B$2459,$Z2) -> 08/01/2024 | AC2: =INDEX(Datos_Origen!$H$2:$H$2459,$Z2) -> 21 | AD2: =INDEX(Datos_Origen!$D$2:$D$2459,$Z2)&"" -> Buenos Aires
A3: =INDEX(Datos_Origen!$A$2:$A$2459,$Z3) -> 2 | B3: =IF(ISNUMBER($AB3),$AB3,IF(MID($AB3,5,1)="-",DATE(VALUE(LEFT($AB3,4)),VALUE(MID($AB3,6,2)),VALUE(RIGHT($AB3,2))),DATE(VALUE(RIGHT($AB3,4)),VALUE(MID($AB3,4,2)),VALUE(LEFT($AB3,2))))) -> 45306 | C3: =YEAR($B3) -> 2024 | D3: ="Q"&ROUNDUP(MONTH($B3)/3,0) -> Q1 | E3: =MONTH($B3) -> 1 | F3: =INDEX(Parametros!$I$5:$I$16,$E3) -> Ene | G3: =TEXT($C3,"0000")&"-"&TEXT($E3,"00") -> 2024-01 | H3: =INDEX(Parametros!$C$71:$C$91,MATCH(TRIM(INDEX(Datos_Origen!$C$2:$C$2459,$Z3)),Parametros!$B$71:$B$91,0)) -> AMBA | I3: =IF(TRIM($AD3)="",INDEX(Parametros!$I$20:$I$24,MATCH($H3,Parametros!$H$20:$H$24,0)),TRIM($AD3)) -> Buenos Aires | J3: =INDEX(Parametros!$C$95:$C$106,MATCH(TRIM(INDEX(Datos_Origen!$E$2:$E$2459,$Z3)),Parametros!$B$95:$B$106,0)) -> E-commerce | K3: =INDEX(Parametros!$C$48:$C$67,MATCH(TRIM(INDEX(Datos_Origen!$F$2:$F$2459,$Z3)),Parametros!$B$48:$B$67,0)) -> Computacion | L3: =$K3&" "&$C3 -> Computacion 2024 | M3: =TRIM(INDEX(Datos_Origen!$G$2:$G$2459,$Z3)) -> Laptop Pro 15 | N3: =$M3&" "&$C3 -> Laptop Pro 15 2024 | O3: =IF(ISTEXT($AC3),VALUE($AC3),$AC3) -> 8 | P3: =INDEX(Datos_Origen!$I$2:$I$2459,$Z3) -> 1176 | Q3: =INDEX(Datos_Origen!$J$2:$J$2459,$Z3) -> 744 | R3: =ROUND($O3*$P3,2) -> 9408 | S3: =ROUND($O3*$Q3,2) -> 5952 | T3: =ROUND($R3*SUMIFS(Parametros!$E$28:$E$43,Parametros!$B$28:$B$43,$J3,Parametros!$C$28:$C$43,$C3,Parametros!$D$28:$D$43,$D3),2) -> 395.14 | U3: =$R3-$S3-$T3 -> 3060.86 | V3: =IFERROR($U3/$R3,0) -> 0.32534651 | W3: =IF(AND($V3>=Parametros!$C$8,$R3>=Parametros!$C$12),"Alta rentabilidad",IF(OR($V3<Parametros!$C$11,$R3<Parametros!$C$13),"Revisar","Estandar")) -> Estandar | X3: =IF(AND($J3="E-commerce",IFERROR($T3/$R3,0)>Parametros!$C$14),"Alerta","OK") -> OK | Y3: =IF($R3>=Parametros!$C$12,"Alto",IF($R3<Parametros!$C$13,"Bajo","Medio")) -> Alto | Z3: 1401 | AA3: =IF(MATCH($A3,Datos_Origen!$A$2:$A$2459,0)=$Z3,"OK","REVISAR") -> OK | AB3: =INDEX(Datos_Origen!$B$2:$B$2459,$Z3) -> 2024-01-15 | AC3: =INDEX(Datos_Origen!$H$2:$H$2459,$Z3) -> 8 | AD3: =INDEX(Datos_Origen!$D$2:$D$2459,$Z3)&"" -> Buenos Aires
A4: =INDEX(Datos_Origen!$A$2:$A$2459,$Z4) -> 3 | B4: =IF(ISNUMBER($AB4),$AB4,IF(MID($AB4,5,1)="-",DATE(VALUE(LEFT($AB4,4)),VALUE(MID($AB4,6,2)),VALUE(RIGHT($AB4,2))),DATE(VALUE(RIGHT($AB4,4)),VALUE(MID($AB4,4,2)),VALUE(LEFT($AB4,2))))) -> 45313 | C4: =YEAR($B4) -> 2024 | D4: ="Q"&ROUNDUP(MONTH($B4)/3,0) -> Q1 | E4: =MONTH($B4) -> 1 | F4: =INDEX(Parametros!$I$5:$I$16,$E4) -> Ene | G4: =TEXT($C4,"0000")&"-"&TEXT($E4,"00") -> 2024-01 | H4: =INDEX(Parametros!$C$71:$C$91,MATCH(TRIM(INDEX(Datos_Origen!$C$2:$C$2459,$Z4)),Parametros!$B$71:$B$91,0)) -> AMBA | I4: =IF(TRIM($AD4)="",INDEX(Parametros!$I$20:$I$24,MATCH($H4,Parametros!$H$20:$H$24,0)),TRIM($AD4)) -> Buenos Aires | J4: =INDEX(Parametros!$C$95:$C$106,MATCH(TRIM(INDEX(Datos_Origen!$E$2:$E$2459,$Z4)),Parametros!$B$95:$B$106,0)) -> Tienda fisica | K4: =INDEX(Parametros!$C$48:$C$67,MATCH(TRIM(INDEX(Datos_Origen!$F$2:$F$2459,$Z4)),Parametros!$B$48:$B$67,0)) -> Computacion | L4: =$K4&" "&$C4 -> Computacion 2024 | M4: =TRIM(INDEX(Datos_Origen!$G$2:$G$2459,$Z4)) -> Monitor 4K 27 | N4: =$M4&" "&$C4 -> Monitor 4K 27 2024 | O4: =IF(ISTEXT($AC4),VALUE($AC4),$AC4) -> 18 | P4: =INDEX(Datos_Origen!$I$2:$I$2459,$Z4) -> 441 | Q4: =INDEX(Datos_Origen!$J$2:$J$2459,$Z4) -> 272.25 | R4: =ROUND($O4*$P4,2) -> 7938 | S4: =ROUND($O4*$Q4,2) -> 4900.5 | T4: =ROUND($R4*SUMIFS(Parametros!$E$28:$E$43,Parametros!$B$28:$B$43,$J4,Parametros!$C$28:$C$43,$C4,Parametros!$D$28:$D$43,$D4),2) -> 95.26 | U4: =$R4-$S4-$T4 -> 2942.24 | V4: =IFERROR($U4/$R4,0) -> 0.37065256 | W4: =IF(AND($V4>=Parametros!$C$8,$R4>=Parametros!$C$12),"Alta rentabilidad",IF(OR($V4<Parametros!$C$11,$R4<Parametros!$C$13),"Revisar","Estandar")) -> Alta rentabilidad | X4: =IF(AND($J4="E-commerce",IFERROR($T4/$R4,0)>Parametros!$C$14),"Alerta","OK") -> OK | Y4: =IF($R4>=Parametros!$C$12,"Alto",IF($R4<Parametros!$C$13,"Bajo","Medio")) -> Alto | Z4: 1921 | AA4: =IF(MATCH($A4,Datos_Origen!$A$2:$A$2459,0)=$Z4,"OK","REVISAR") -> OK | AB4: =INDEX(Datos_Origen!$B$2:$B$2459,$Z4) -> 2024-01-22 | AC4: =INDEX(Datos_Origen!$H$2:$H$2459,$Z4) -> 18 | AD4: =INDEX(Datos_Origen!$D$2:$D$2459,$Z4)&""
A5: =INDEX(Datos_Origen!$A$2:$A$2459,$Z5) -> 4 | B5: =IF(ISNUMBER($AB5),$AB5,IF(MID($AB5,5,1)="-",DATE(VALUE(LEFT($AB5,4)),VALUE(MID($AB5,6,2)),VALUE(RIGHT($AB5,2))),DATE(VALUE(RIGHT($AB5,4)),VALUE(MID($AB5,4,2)),VALUE(LEFT($AB5,2))))) -> 45293 | C5: =YEAR($B5) -> 2024 | D5: ="Q"&ROUNDUP(MONTH($B5)/3,0) -> Q1 | E5: =MONTH($B5) -> 1 | F5: =INDEX(Parametros!$I$5:$I$16,$E5) -> Ene | G5: =TEXT($C5,"0000")&"-"&TEXT($E5,"00") -> 2024-01 | H5: =INDEX(Parametros!$C$71:$C$91,MATCH(TRIM(INDEX(Datos_Origen!$C$2:$C$2459,$Z5)),Parametros!$B$71:$B$91,0)) -> AMBA | I5: =IF(TRIM($AD5)="",INDEX(Parametros!$I$20:$I$24,MATCH($H5,Parametros!$H$20:$H$24,0)),TRIM($AD5)) -> Buenos Aires | J5: =INDEX(Parametros!$C$95:$C$106,MATCH(TRIM(INDEX(Datos_Origen!$E$2:$E$2459,$Z5)),Parametros!$B$95:$B$106,0)) -> E-commerce | K5: =INDEX(Parametros!$C$48:$C$67,MATCH(TRIM(INDEX(Datos_Origen!$F$2:$F$2459,$Z5)),Parametros!$B$48:$B$67,0)) -> Computacion | L5: =$K5&" "&$C5 -> Computacion 2024 | M5: =TRIM(INDEX(Datos_Origen!$G$2:$G$2459,$Z5)) -> Monitor 4K 27 | N5: =$M5&" "&$C5 -> Monitor 4K 27 2024 | O5: =IF(ISTEXT($AC5),VALUE($AC5),$AC5) -> 8 | P5: =INDEX(Datos_Origen!$I$2:$I$2459,$Z5) -> 441 | Q5: =INDEX(Datos_Origen!$J$2:$J$2459,$Z5) -> 272.25 | R5: =ROUND($O5*$P5,2) -> 3528 | S5: =ROUND($O5*$Q5,2) -> 2178 | T5: =ROUND($R5*SUMIFS(Parametros!$E$28:$E$43,Parametros!$B$28:$B$43,$J5,Parametros!$C$28:$C$43,$C5,Parametros!$D$28:$D$43,$D5),2) -> 148.18 | U5: =$R5-$S5-$T5 -> 1201.82 | V5: =IFERROR($U5/$R5,0) -> 0.34065193 | W5: =IF(AND($V5>=Parametros!$C$8,$R5>=Parametros!$C$12),"Alta rentabilidad",IF(OR($V5<Parametros!$C$11,$R5<Parametros!$C$13),"Revisar","Estandar")) -> Alta rentabilidad | X5: =IF(AND($J5="E-commerce",IFERROR($T5/$R5,0)>Parametros!$C$14),"Alerta","OK") -> OK | Y5: =IF($R5>=Parametros!$C$12,"Alto",IF($R5<Parametros!$C$13,"Bajo","Medio")) -> Alto | Z5: 2435 | AA5: =IF(MATCH($A5,Datos_Origen!$A$2:$A$2459,0)=$Z5,"OK","REVISAR") -> OK | AB5: =INDEX(Datos_Origen!$B$2:$B$2459,$Z5) -> 45293 | AC5: =INDEX(Datos_Origen!$H$2:$H$2459,$Z5) -> 8 | AD5: =INDEX(Datos_Origen!$D$2:$D$2459,$Z5)&"" -> Buenos Aires
A6: =INDEX(Datos_Origen!$A$2:$A$2459,$Z6) -> 5 | B6: =IF(ISNUMBER($AB6),$AB6,IF(MID($AB6,5,1)="-",DATE(VALUE(LEFT($AB6,4)),VALUE(MID($AB6,6,2)),VALUE(RIGHT($AB6,2))),DATE(VALUE(RIGHT($AB6,4)),VALUE(MID($AB6,4,2)),VALUE(LEFT($AB6,2))))) -> 45300 | C6: =YEAR($B6) -> 2024 | D6: ="Q"&ROUNDUP(MONTH($B6)/3,0) -> Q1 | E6: =MONTH($B6) -> 1 | F6: =INDEX(Parametros!$I$5:$I$16,$E6) -> Ene | G6: =TEXT($C6,"0000")&"-"&TEXT($E6,"00") -> 2024-01 | H6: =INDEX(Parametros!$C$71:$C$91,MATCH(TRIM(INDEX(Datos_Origen!$C$2:$C$2459,$Z6)),Parametros!$B$71:$B$91,0)) -> AMBA | I6: =IF(TRIM($AD6)="",INDEX(Parametros!$I$20:$I$24,MATCH($H6,Parametros!$H$20:$H$24,0)),TRIM($AD6)) -> Buenos Aires | J6: =INDEX(Parametros!$C$95:$C$106,MATCH(TRIM(INDEX(Datos_Origen!$E$2:$E$2459,$Z6)),Parametros!$B$95:$B$106,0)) -> Tienda fisica | K6: =INDEX(Parametros!$C$48:$C$67,MATCH(TRIM(INDEX(Datos_Origen!$F$2:$F$2459,$Z6)),Parametros!$B$48:$B$67,0)) -> Computacion | L6: =$K6&" "&$C6 -> Computacion 2024 | M6: =TRIM(INDEX(Datos_Origen!$G$2:$G$2459,$Z6)) -> PC Gamer Ryzen | N6: =$M6&" "&$C6 -> PC Gamer Ryzen 2024 | O6: =IF(ISTEXT($AC6),VALUE($AC6),$AC6) -> 19 | P6: =INDEX(Datos_Origen!$I$2:$I$2459,$Z6) -> 1617 | Q6: =INDEX(Datos_Origen!$J$2:$J$2459,$Z6) -> 1122 | R6: =ROUND($O6*$P6,2) -> 30723 | S6: =ROUND($O6*$Q6,2) -> 21318 | T6: =ROUND($R6*SUMIFS(Parametros!$E$28:$E$43,Parametros!$B$28:$B$43,$J6,Parametros!$C$28:$C$43,$C6,Parametros!$D$28:$D$43,$D6),2) -> 368.68 | U6: =$R6-$S6-$T6 -> 9036.32 | V6: =IFERROR($U6/$R6,0) -> 0.29412232 | W6: =IF(AND($V6>=Parametros!$C$8,$R6>=Parametros!$C$12),"Alta rentabilidad",IF(OR($V6<Parametros!$C$11,$R6<Parametros!$C$13),"Revisar","Estandar")) -> Estandar | X6: =IF(AND($J6="E-commerce",IFERROR($T6/$R6,0)>Parametros!$C$14),"Alerta","OK") -> OK | Y6: =IF($R6>=Parametros!$C$12,"Alto",IF($R6<Parametros!$C$13,"Bajo","Medio")) -> Alto | Z6: 242 | AA6: =IF(MATCH($A6,Datos_Origen!$A$2:$A$2459,0)=$Z6,"OK","REVISAR") -> OK | AB6: =INDEX(Datos_Origen!$B$2:$B$2459,$Z6) -> 45300 | AC6: =INDEX(Datos_Origen!$H$2:$H$2459,$Z6) -> 19 | AD6: =INDEX(Datos_Origen!$D$2:$D$2459,$Z6)&"" -> Buenos Aires
A7: =INDEX(Datos_Origen!$A$2:$A$2459,$Z7) -> 6 | B7: =IF(ISNUMBER($AB7),$AB7,IF(MID($AB7,5,1)="-",DATE(VALUE(LEFT($AB7,4)),VALUE(MID($AB7,6,2)),VALUE(RIGHT($AB7,2))),DATE(VALUE(RIGHT($AB7,4)),VALUE(MID($AB7,4,2)),VALUE(LEFT($AB7,2))))) -> 45307 | C7: =YEAR($B7) -> 2024 | D7: ="Q"&ROUNDUP(MONTH($B7)/3,0) -> Q1 | E7: =MONTH($B7) -> 1 | F7: =INDEX(Parametros!$I$5:$I$16,$E7) -> Ene | G7: =TEXT($C7,"0000")&"-"&TEXT($E7,"00") -> 2024-01 | H7: =INDEX(Parametros!$C$71:$C$91,MATCH(TRIM(INDEX(Datos_Origen!$C$2:$C$2459,$Z7)),Parametros!$B$71:$B$91,0)) -> AMBA | I7: =IF(TRIM($AD7)="",INDEX(Parametros!$I$20:$I$24,MATCH($H7,Parametros!$H$20:$H$24,0)),TRIM($AD7)) -> Buenos Aires | J7: =INDEX(Parametros!$C$95:$C$106,MATCH(TRIM(INDEX(Datos_Origen!$E$2:$E$2459,$Z7)),Parametros!$B$95:$B$106,0)) -> E-commerce | K7: =INDEX(Parametros!$C$48:$C$67,MATCH(TRIM(INDEX(Datos_Origen!$F$2:$F$2459,$Z7)),Parametros!$B$48:$B$67,0)) -> Computacion | L7: =$K7&" "&$C7 -> Computacion 2024 | M7: =TRIM(INDEX(Datos_Origen!$G$2:$G$2459,$Z7)) -> PC Gamer Ryzen | N7: =$M7&" "&$C7 -> PC Gamer Ryzen 2024 | O7: =IF(ISTEXT($AC7),VALUE($AC7),$AC7) -> 8 | P7: =INDEX(Datos_Origen!$I$2:$I$2459,$Z7) -> 1617 | Q7: =INDEX(Datos_Origen!$J$2:$J$2459,$Z7) -> 1122 | R7: =ROUND($O7*$P7,2) -> 12936 | S7: =ROUND($O7*$Q7,2) -> 8976 | T7: =ROUND($R7*SUMIFS(Parametros!$E$28:$E$43,Parametros!$B$28:$B$43,$J7,Parametros!$C$28:$C$43,$C7,Parametros!$D$28:$D$43,$D7),2) -> 543.31 | U7: =$R7-$S7-$T7 -> 3416.69 | V7: =IFERROR($U7/$R7,0) -> 0.2641226 | W7: =IF(AND($V7>=Parametros!$C$8,$R7>=Parametros!$C$12),"Alta rentabilidad",IF(OR($V7<Parametros!$C$11,$R7<Parametros!$C$13),"Revisar","Estandar")) -> Revisar | X7: =IF(AND($J7="E-commerce",IFERROR($T7/$R7,0)>Parametros!$C$14),"Alerta","OK") -> OK | Y7: =IF($R7>=Parametros!$C$12,"Alto",IF($R7<Parametros!$C$13,"Bajo","Medio")) -> Alto | Z7: 134 | AA7: =IF(MATCH($A7,Datos_Origen!$A$2:$A$2459,0)=$Z7,"OK","REVISAR") -> OK | AB7: =INDEX(Datos_Origen!$B$2:$B$2459,$Z7) -> 45307 | AC7: =INDEX(Datos_Origen!$H$2:$H$2459,$Z7) -> 8 | AD7: =INDEX(Datos_Origen!$D$2:$D$2459,$Z7)&"" -> Buenos Aires
A8: =INDEX(Datos_Origen!$A$2:$A$2459,$Z8) -> 7 | B8: =IF(ISNUMBER($AB8),$AB8,IF(MID($AB8,5,1)="-",DATE(VALUE(LEFT($AB8,4)),VALUE(MID($AB8,6,2)),VALUE(RIGHT($AB8,2))),DATE(VALUE(RIGHT($AB8,4)),VALUE(MID($AB8,4,2)),VALUE(LEFT($AB8,2))))) -> 45314 | C8: =YEAR($B8) -> 2024 | D8: ="Q"&ROUNDUP(MONTH($B8)/3,0) -> Q1 | E8: =MONTH($B8) -> 1 | F8: =INDEX(Parametros!$I$5:$I$16,$E8) -> Ene | G8: =TEXT($C8,"0000")&"-"&TEXT($E8,"00") -> 2024-01 | H8: =INDEX(Parametros!$C$71:$C$91,MATCH(TRIM(INDEX(Datos_Origen!$C$2:$C$2459,$Z8)),Parametros!$B$71:$B$91,0)) -> AMBA | I8: =IF(TRIM($AD8)="",INDEX(Parametros!$I$20:$I$24,MATCH($H8,Parametros!$H$20:$H$24,0)),TRIM($AD8)) -> Buenos Aires | J8: =INDEX(Parametros!$C$95:$C$106,MATCH(TRIM(INDEX(Datos_Origen!$E$2:$E$2459,$Z8)),Parametros!$B$95:$B$106,0)) -> Tienda fisica | K8: =INDEX(Parametros!$C$48:$C$67,MATCH(TRIM(INDEX(Datos_Origen!$F$2:$F$2459,$Z8)),Parametros!$B$48:$B$67,0)) -> Accesorios | L8: =$K8&" "&$C8 -> Accesorios 2024 | M8: =TRIM(INDEX(Datos_Origen!$G$2:$G$2459,$Z8)) -> Mouse Inalambrico | N8: =$M8&" "&$C8 -> Mouse Inalambrico 2024 | O8: =IF(ISTEXT($AC8),VALUE($AC8),$AC8) -> 91 | P8: =INDEX(Datos_Origen!$I$2:$I$2459,$Z8) -> 27.44 | Q8: =INDEX(Datos_Origen!$J$2:$J$2459,$Z8) -> 13.44 | R8: =ROUND($O8*$P8,2) -> 2497.04 | S8: =ROUND($O8*$Q8,2) -> 1223.04 | T8: =ROUND($R8*SUMIFS(Parametros!$E$28:$E$43,Parametros!$B$28:$B$43,$J8,Parametros!$C$28:$C$43,$C8,Parametros!$D$28:$D$43,$D8),2) -> 29.96 | U8: =$R8-$S8-$T8 -> 1244.04 | V8: =IFERROR($U8/$R8,0) -> 0.49820588 | W8: =IF(AND($V8>=Parametros!$C$8,$R8>=Parametros!$C$12),"Alta rentabilidad",IF(OR($V8<Parametros!$C$11,$R8<Parametros!$C$13),"Revisar","Estandar")) -> Estandar | X8: =IF(AND($J8="E-commerce",IFERROR($T8/$R8,0)>Parametros!$C$14),"Alerta","OK") -> OK | Y8: =IF($R8>=Parametros!$C$12,"Alto",IF($R8<Parametros!$C$13,"Bajo","Medio")) -> Medio | Z8: 1285 | AA8: =IF(MATCH($A8,Datos_Origen!$A$2:$A$2459,0)=$Z8,"OK","REVISAR") -> OK | AB8: =INDEX(Datos_Origen!$B$2:$B$2459,$Z8) -> 45314 | AC8: =INDEX(Datos_Origen!$H$2:$H$2459,$Z8) -> 91 | AD8: =INDEX(Datos_Origen!$D$2:$D$2459,$Z8)&"" -> Buenos Aires
A9: =INDEX(Datos_Origen!$A$2:$A$2459,$Z9) -> 8 | B9: =IF(ISNUMBER($AB9),$AB9,IF(MID($AB9,5,1)="-",DATE(VALUE(LEFT($AB9,4)),VALUE(MID($AB9,6,2)),VALUE(RIGHT($AB9,2))),DATE(VALUE(RIGHT($AB9,4)),VALUE(MID($AB9,4,2)),VALUE(LEFT($AB9,2))))) -> 45294 | C9: =YEAR($B9) -> 2024 | D9: ="Q"&ROUNDUP(MONTH($B9)/3,0) -> Q1 | E9: =MONTH($B9) -> 1 | F9: =INDEX(Parametros!$I$5:$I$16,$E9) -> Ene | G9: =TEXT($C9,"0000")&"-"&TEXT($E9,"00") -> 2024-01 | H9: =INDEX(Parametros!$C$71:$C$91,MATCH(TRIM(INDEX(Datos_Origen!$C$2:$C$2459,$Z9)),Parametros!$B$71:$B$91,0)) -> AMBA | I9: =IF(TRIM($AD9)="",INDEX(Parametros!$I$20:$I$24,MATCH($H9,Parametros!$H$20:$H$24,0)),TRIM($AD9)) -> Buenos Aires | J9: =INDEX(Parametros!$C$95:$C$106,MATCH(TRIM(INDEX(Datos_Origen!$E$2:$E$2459,$Z9)),Parametros!$B$95:$B$106,0)) -> E-commerce | K9: =INDEX(Parametros!$C$48:$C$67,MATCH(TRIM(INDEX(Datos_Origen!$F$2:$F$2459,$Z9)),Parametros!$B$48:$B$67,0)) -> Accesorios | L9: =$K9&" "&$C9 -> Accesorios 2024 | M9: =TRIM(INDEX(Datos_Origen!$G$2:$G$2459,$Z9)) -> Mouse Inalambrico | N9: =$M9&" "&$C9 -> Mouse Inalambrico 2024 | O9: =IF(ISTEXT($AC9),VALUE($AC9),$AC9) -> 30 | P9: =INDEX(Datos_Origen!$I$2:$I$2459,$Z9) -> 27.44 | Q9: =INDEX(Datos_Origen!$J$2:$J$2459,$Z9) -> 13.44 | R9: =ROUND($O9*$P9,2) -> 823.2 | S9: =ROUND($O9*$Q9,2) -> 403.2 | T9: =ROUND($R9*SUMIFS(Parametros!$E$28:$E$43,Parametros!$B$28:$B$43,$J9,Parametros!$C$28:$C$43,$C9,Parametros!$D$28:$D$43,$D9),2) -> 34.57 | U9: =$R9-$S9-$T9 -> 385.43 | V9: =IFERROR($U9/$R9,0) -> 0.46820943 | W9: =IF(AND($V9>=Parametros!$C$8,$R9>=Parametros!$C$12),"Alta rentabilidad",IF(OR($V9<Parametros!$C$11,$R9<Parametros!$C$13),"Revisar","Estandar")) -> Estandar | X9: =IF(AND($J9="E-commerce",IFERROR($T9/$R9,0)>Parametros!$C$14),"Alerta","OK") -> OK | Y9: =IF($R9>=Parametros!$C$12,"Alto",IF($R9<Parametros!$C$13,"Bajo","Medio")) -> Medio | Z9: 3 | AA9: =IF(MATCH($A9,Datos_Origen!$A$2:$A$2459,0)=$Z9,"OK","REVISAR") -> OK | AB9: =INDEX(Datos_Origen!$B$2:$B$2459,$Z9) -> 03/01/2024 | AC9: =INDEX(Datos_Origen!$H$2:$H$2459,$Z9) -> 30 | AD9: =INDEX(Datos_Origen!$D$2:$D$2459,$Z9)&"" -> Buenos Aires
A10: =INDEX(Datos_Origen!$A$2:$A$2459,$Z10) -> 9 | B10: =IF(ISNUMBER($AB10),$AB10,IF(MID($AB10,5,1)="-",DATE(VALUE(LEFT($AB10,4)),VALUE(MID($AB10,6,2)),VALUE(RIGHT($AB10,2))),DATE(VALUE(RIGHT($AB10,4)),VALUE(MID($AB10,4,2)),VALUE(LEFT($AB10,2))))) -> 45301 | C10: =YEAR($B10) -> 2024 | D10: ="Q"&ROUNDUP(MONTH($B10)/3,0) -> Q1 | E10: =MONTH($B10) -> 1 | F10: =INDEX(Parametros!$I$5:$I$16,$E10) -> Ene | G10: =TEXT($C10,"0000")&"-"&TEXT($E10,"00") -> 2024-01 | H10: =INDEX(Parametros!$C$71:$C$91,MATCH(TRIM(INDEX(Datos_Origen!$C$2:$C$2459,$Z10)),Parametros!$B$71:$B$91,0)) -> AMBA | I10: =IF(TRIM($AD10)="",INDEX(Parametros!$I$20:$I$24,MATCH($H10,Parametros!$H$20:$H$24,0)),TRIM($AD10)) -> Buenos Aires | J10: =INDEX(Parametros!$C$95:$C$106,MATCH(TRIM(INDEX(Datos_Origen!$E$2:$E$2459,$Z10)),Parametros!$B$95:$B$106,0)) -> Tienda fisica | K10: =INDEX(Parametros!$C$48:$C$67,MATCH(TRIM(INDEX(Datos_Origen!$F$2:$F$2459,$Z10)),Parametros!$B$48:$B$67,0)) -> Accesorios | L10: =$K10&" "&$C10 -> Accesorios 2024 | M10: =TRIM(INDEX(Datos_Origen!$G$2:$G$2459,$Z10)) -> Teclado Mecanico | N10: =$M10&" "&$C10 -> Teclado Mecanico 2024 | O10: =IF(ISTEXT($AC10),VALUE($AC10),$AC10) -> 95 | P10: =INDEX(Datos_Origen!$I$2:$I$2459,$Z10) -> 93.1 | Q10: =INDEX(Datos_Origen!$J$2:$J$2459,$Z10) -> 47.98 | R10: =ROUND($O10*$P10,2) -> 8844.5 | S10: =ROUND($O10*$Q10,2) -> 4558.1 | T10: =ROUND($R10*SUMIFS(Parametros!$E$28:$E$43,Parametros!$B$28:$B$43,$J10,Parametros!$C$28:$C$43,$C10,Parametros!$D$28:$D$43,$D10),2) -> 106.13 | U10: =$R10-$S10-$T10 -> 4180.27 | V10: =IFERROR($U10/$R10,0) -> 0.47264062 | W10: =IF(AND($V10>=Parametros!$C$8,$R10>=Parametros!$C$12),"Alta rentabilidad",IF(OR($V10<Parametros!$C$11,$R10<Parametros!$C$13),"Revisar","Estandar")) -> Alta rentabilidad | X10: =IF(AND($J10="E-commerce",IFERROR($T10/$R10,0)>Parametros!$C$14),"Alerta","OK") -> OK | Y10: =IF($R10>=Parametros!$C$12,"Alto",IF($R10<Parametros!$C$13,"Bajo","Medio")) -> Alto | Z10: 1967 | AA10: =IF(MATCH($A10,Datos_Origen!$A$2:$A$2459,0)=$Z10,"OK","REVISAR") -> OK | AB10: =INDEX(Datos_Origen!$B$2:$B$2459,$Z10) -> 2024-01-10 | AC10: =INDEX(Datos_Origen!$H$2:$H$2459,$Z10) -> 95 | AD10: =INDEX(Datos_Origen!$D$2:$D$2459,$Z10)&"" -> Buenos Aires
A11: =INDEX(Datos_Origen!$A$2:$A$2459,$Z11) -> 10 | B11: =IF(ISNUMBER($AB11),$AB11,IF(MID($AB11,5,1)="-",DATE(VALUE(LEFT($AB11,4)),VALUE(MID($AB11,6,2)),VALUE(RIGHT($AB11,2))),DATE(VALUE(RIGHT($AB11,4)),VALUE(MID($AB11,4,2)),VALUE(LEFT($AB11,2))))) -> 45308 | C11: =YEAR($B11) -> 2024 | D11: ="Q"&ROUNDUP(MONTH($B11)/3,0) -> Q1 | E11: =MONTH($B11) -> 1 | F11: =INDEX(Parametros!$I$5:$I$16,$E11) -> Ene | G11: =TEXT($C11,"0000")&"-"&TEXT($E11,"00") -> 2024-01 | H11: =INDEX(Parametros!$C$71:$C$91,MATCH(TRIM(INDEX(Datos_Origen!$C$2:$C$2459,$Z11)),Parametros!$B$71:$B$91,0)) -> AMBA | I11: =IF(TRIM($AD11)="",INDEX(Parametros!$I$20:$I$24,MATCH($H11,Parametros!$H$20:$H$24,0)),TRIM($AD11)) -> Buenos Aires | J11: =INDEX(Parametros!$C$95:$C$106,MATCH(TRIM(INDEX(Datos_Origen!$E$2:$E$2459,$Z11)),Parametros!$B$95:$B$106,0)) -> E-commerce | K11: =INDEX(Parametros!$C$48:$C$67,MATCH(TRIM(INDEX(Datos_Origen!$F$2:$F$2459,$Z11)),Parametros!$B$48:$B$67,0)) -> Accesorios | L11: =$K11&" "&$C11 -> Accesorios 2024 | M11: =TRIM(INDEX(Datos_Origen!$G$2:$G$2459,$Z11)) -> Teclado Mecanico | N11: =$M11&" "&$C11 -> Teclado Mecanico 2024 | O11: =IF(ISTEXT($AC11),VALUE($AC11),$AC11) -> 35 | P11: =INDEX(Datos_Origen!$I$2:$I$2459,$Z11) -> 93.1 | Q11: =INDEX(Datos_Origen!$J$2:$J$2459,$Z11) -> 47.98 | R11: =ROUND($O11*$P11,2) -> 3258.5 | S11: =ROUND($O11*$Q11,2) -> 1679.3 | T11: =ROUND($R11*SUMIFS(Parametros!$E$28:$E$43,Parametros!$B$28:$B$43,$J11,Parametros!$C$28:$C$43,$C11,Parametros!$D$28:$D$43,$D11),2) -> 136.86 | U11: =$R11-$S11-$T11 -> 1442.34 | V11: =IFERROR($U11/$R11,0) -> 0.44263925 | W11: =IF(AND($V11>=Parametros!$C$8,$R11>=Parametros!$C$12),"Alta rentabilidad",IF(OR($V11<Parametros!$C$11,$R11<Parametros!$C$13),"Revisar","Estandar")) -> Alta rentabilidad | X11: =IF(AND($J11="E-commerce",IFERROR($T11/$R11,0)>Parametros!$C$14),"Alerta","OK") -> OK | Y11: =IF($R11>=Parametros!$C$12,"Alto",IF($R11<Parametros!$C$13,"Bajo","Medio")) -> Alto | Z11: 1971 | AA11: =IF(MATCH($A11,Datos_Origen!$A$2:$A$2459,0)=$Z11,"OK","REVISAR") -> OK | AB11: =INDEX(Datos_Origen!$B$2:$B$2459,$Z11) -> 45308 | AC11: =INDEX(Datos_Origen!$H$2:$H$2459,$Z11) -> 35 | AD11: =INDEX(Datos_Origen!$D$2:$D$2459,$Z11)&"" -> Buenos Aires
A12: =INDEX(Datos_Origen!$A$2:$A$2459,$Z12) -> 11 | B12: =IF(ISNUMBER($AB12),$AB12,IF(MID($AB12,5,1)="-",DATE(VALUE(LEFT($AB12,4)),VALUE(MID($AB12,6,2)),VALUE(RIGHT($AB12,2))),DATE(VALUE(RIGHT($AB12,4)),VALUE(MID($AB12,4,2)),VALUE(LEFT($AB12,2))))) -> 45315 | C12: =YEAR($B12) -> 2024 | D12: ="Q"&ROUNDUP(MONTH($B12)/3,0) -> Q1 | E12: =MONTH($B12) -> 1 | F12: =INDEX(Parametros!$I$5:$I$16,$E12) -> Ene | G12: =TEXT($C12,"0000")&"-"&TEXT($E12,"00") -> 2024-01 | H12: =INDEX(Parametros!$C$71:$C$91,MATCH(TRIM(INDEX(Datos_Origen!$C$2:$C$2459,$Z12)),Parametros!$B$71:$B$91,0)) -> AMBA | I12: =IF(TRIM($AD12)="",INDEX(Parametros!$I$20:$I$24,MATCH($H12,Parametros!$H$20:$H$24,0)),TRIM($AD12)) -> Buenos Aires | J12: =INDEX(Parametros!$C$95:$C$106,MATCH(TRIM(INDEX(Datos_Origen!$E$2:$E$2459,$Z12)),Parametros!$B$95:$B$106,0)) -> Tienda fisica | K12: =INDEX(Parametros!$C$48:$C$67,MATCH(TRIM(INDEX(Datos_Origen!$F$2:$F$2459,$Z12)),Parametros!$B$48:$B$67,0)) -> Accesorios | L12: =$K12&" "&$C12 -> Accesorios 2024 | M12: =TRIM(INDEX(Datos_Origen!$G$2:$G$2459,$Z12)) -> Webcam Full HD | N12: =$M12&" "&$C12 -> Webcam Full HD 2024 | O12: =IF(ISTEXT($AC12),VALUE($AC12),$AC12) -> 98 | P12: =INDEX(Datos_Origen!$I$2:$I$2459,$Z12) -> 63.7 | Q12: =INDEX(Datos_Origen!$J$2:$J$2459,$Z12) -> 35.43 | R12: =ROUND($O12*$P12,2) -> 6242.6 | S12: =ROUND($O12*$Q12,2) -> 3472.14 | T12: =ROUND($R12*SUMIFS(Parametros!$E$28:$E$43,Parametros!$B$28:$B$43,$J12,Parametros!$C$28:$C$43,$C12,Parametros!$D$28:$D$43,$D12),2) -> 74.91 | U12: =$R12-$S12-$T12 -> 2695.55 | V12: =IFERROR($U12/$R12,0) -> 0.43179925 | W12: =IF(AND($V12>=Parametros!$C$8,$R12>=Parametros!$C$12),"Alta rentabilidad",IF(OR($V12<Parametros!$C$11,$R12<Parametros!$C$13),"Revisar","Estandar")) -> Alta rentabilidad | X12: =IF(AND($J12="E-commerce",IFERROR($T12/$R12,0)>Parametros!$C$14),"Alerta","OK") -> OK | Y12: =IF($R12>=Parametros!$C$12,"Alto",IF($R12<Parametros!$C$13,"Bajo","Medio")) -> Alto | Z12: 1546 | AA12: =IF(MATCH($A12,Datos_Origen!$A$2:$A$2459,0)=$Z12,"OK","REVISAR") -> OK | AB12: =INDEX(Datos_Origen!$B$2:$B$2459,$Z12) -> 45315 | AC12: =INDEX(Datos_Origen!$H$2:$H$2459,$Z12) -> 98 | AD12: =INDEX(Datos_Origen!$D$2:$D$2459,$Z12)&"" -> Buenos Aires
A13: =INDEX(Datos_Origen!$A$2:$A$2459,$Z13) -> 12 | B13: =IF(ISNUMBER($AB13),$AB13,IF(MID($AB13,5,1)="-",DATE(VALUE(LEFT($AB13,4)),VALUE(MID($AB13,6,2)),VALUE(RIGHT($AB13,2))),DATE(VALUE(RIGHT($AB13,4)),VALUE(MID($AB13,4,2)),VALUE(LEFT($AB13,2))))) -> 45295 | C13: =YEAR($B13) -> 2024 | D13: ="Q"&ROUNDUP(MONTH($B13)/3,0) -> Q1 | E13: =MONTH($B13) -> 1 | F13: =INDEX(Parametros!$I$5:$I$16,$E13) -> Ene | G13: =TEXT($C13,"0000")&"-"&TEXT($E13,"00") -> 2024-01 | H13: =INDEX(Parametros!$C$71:$C$91,MATCH(TRIM(INDEX(Datos_Origen!$C$2:$C$2459,$Z13)),Parametros!$B$71:$B$91,0)) -> AMBA | I13: =IF(TRIM($AD13)="",INDEX(Parametros!$I$20:$I$24,MATCH($H13,Parametros!$H$20:$H$24,0)),TRIM($AD13)) -> Buenos Aires | J13: =INDEX(Parametros!$C$95:$C$106,MATCH(TRIM(INDEX(Datos_Origen!$E$2:$E$2459,$Z13)),Parametros!$B$95:$B$106,0)) -> E-commerce | K13: =INDEX(Parametros!$C$48:$C$67,MATCH(TRIM(INDEX(Datos_Origen!$F$2:$F$2459,$Z13)),Parametros!$B$48:$B$67,0)) -> Accesorios | L13: =$K13&" "&$C13 -> Accesorios 2024 | M13: =TRIM(INDEX(Datos_Origen!$G$2:$G$2459,$Z13)) -> Webcam Full HD | N13: =$M13&" "&$C13 -> Webcam Full HD 2024 | O13: =IF(ISTEXT($AC13),VALUE($AC13),$AC13) -> 32 | P13: =INDEX(Datos_Origen!$I$2:$I$2459,$Z13) -> 63.7 | Q13: =INDEX(Datos_Origen!$J$2:$J$2459,$Z13) -> 35.43 | R13: =ROUND($O13*$P13,2) -> 2038.4 | S13: =ROUND($O13*$Q13,2) -> 1133.76 | T13: =ROUND($R13*SUMIFS(Parametros!$E$28:$E$43,Parametros!$B$28:$B$43,$J13,Parametros!$C$28:$C$43,$C13,Parametros!$D$28:$D$43,$D13),2) -> 85.61 | U13: =$R13-$S13-$T13 -> 819.03 | V13: =IFERROR($U13/$R13,0) -> 0.40180043 | W13: =IF(AND($V13>=Parametros!$C$8,$R13>=Parametros!$C$12),"Alta rentabilidad",IF(OR($V13<Parametros!$C$11,$R13<Parametros!$C$13),"Revisar","Estandar")) -> Estandar | X13: =IF(AND($J13="E-commerce",IFERROR($T13/$R13,0)>Parametros!$C$14),"Alerta","OK") -> OK | Y13: =IF($R13>=Parametros!$C$12,"Alto",IF($R13<Parametros!$C$13,"Bajo","Medio")) -> Medio | Z13: 303 | AA13: =IF(MATCH($A13,Datos_Origen!$A$2:$A$2459,0)=$Z13,"OK","REVISAR") -> OK | AB13: =INDEX(Datos_Origen!$B$2:$B$2459,$Z13) -> 45295 | AC13: =INDEX(Datos_Origen!$H$2:$H$2459,$Z13) -> 32 | AD13: =INDEX(Datos_Origen!$D$2:$D$2459,$Z13)&"" -> Buenos Aires
... A2401: =INDEX(Datos_Origen!$A$2:$A$2459,$Z2401) -> 2400 | B2401: =IF(ISNUMBER($AB2401),$AB2401,IF(MID($AB2401,5,1)="-",DATE(VALUE(LEFT($AB2401,4)),VALUE(MID($AB2401,6,2)),VALUE(RIGHT($AB2401,2))),DATE(VALUE(RIGHT($AB2401,4)),VALUE(MID($AB2401,4,2)),VALUE(LEFT($AB2401,2))))) -> 45998 | C2401: =YEAR($B2401) -> 2025 | D2401: ="Q"&ROUNDUP(MONTH($B2401)/3,0) -> Q4 | E2401: =MONTH($B2401) -> 12 | F2401: =INDEX(Parametros!$I$5:$I$16,$E2401) -> Dic | G2401: =TEXT($C2401,"0000")&"-"&TEXT($E2401,"00") -> 2025-12 | H2401: =INDEX(Parametros!$C$71:$C$91,MATCH(TRIM(INDEX(Datos_Origen!$C$2:$C$2459,$Z2401)),Parametros!$B$71:$B$91,0)) -> NOA | I2401: =IF(TRIM($AD2401)="",INDEX(Parametros!$I$20:$I$24,MATCH($H2401,Parametros!$H$20:$H$24,0)),TRIM($AD2401)) -> Tucuman | J2401: =INDEX(Parametros!$C$95:$C$106,MATCH(TRIM(INDEX(Datos_Origen!$E$2:$E$2459,$Z2401)),Parametros!$B$95:$B$106,0)) -> E-commerce | K2401: =INDEX(Parametros!$C$48:$C$67,MATCH(TRIM(INDEX(Datos_Origen!$F$2:$F$2459,$Z2401)),Parametros!$B$48:$B$67,0)) -> Almacenamiento | L2401: =$K2401&" "&$C2401 -> Almacenamiento 2025 | M2401: =TRIM(INDEX(Datos_Origen!$G$2:$G$2459,$Z2401)) -> Pendrive 256GB | N2401: =$M2401&" "&$C2401 -> Pendrive 256GB 2025 | O2401: =IF(ISTEXT($AC2401),VALUE($AC2401),$AC2401) -> 17 | P2401: =INDEX(Datos_Origen!$I$2:$I$2459,$Z2401) -> 35.14 | Q2401: =INDEX(Datos_Origen!$J$2:$J$2459,$Z2401) -> 18.39 | R2401: =ROUND($O2401*$P2401,2) -> 597.38 | S2401: =ROUND($O2401*$Q2401,2) -> 312.63 | T2401: =ROUND($R2401*SUMIFS(Parametros!$E$28:$E$43,Parametros!$B$28:$B$43,$J2401,Parametros!$C$28:$C$43,$C2401,Parametros!$D$28:$D$43,$D2401),2) -> 31.06 | U2401: =$R2401-$S2401-$T2401 -> 253.69 | V2401: =IFERROR($U2401/$R2401,0) -> 0.42467106 | W2401: =IF(AND($V2401>=Parametros!$C$8,$R2401>=Parametros!$C$12),"Alta rentabilidad",IF(OR($V2401<Parametros!$C$11,$R2401<Parametros!$C$13),"Revisar","Estandar")) -> Estandar | X2401: =IF(AND($J2401="E-commerce",IFERROR($T2401/$R2401,0)>Parametros!$C$14),"Alerta","OK") -> Alerta | Y2401: =IF($R2401>=Parametros!$C$12,"Alto",IF($R2401<Parametros!$C$13,"Bajo","Medio")) -> Medio | Z2401: 2149 | AA2401: =IF(MATCH($A2401,Datos_Origen!$A$2:$A$2459,0)=$Z2401,"OK","REVISAR") -> OK | AB2401: =INDEX(Datos_Origen!$B$2:$B$2459,$Z2401) -> 45998 | AC2401: =INDEX(Datos_Origen!$H$2:$H$2459,$Z2401) -> 17 | AD2401: =INDEX(Datos_Origen!$D$2:$D$2459,$Z2401)&"" -> Tucuman

Sheet Datos_Origen
A1: ID_Venta | B1: Fecha | C1: Region | D1: Ciudad | E1: Canal | F1: Categoria | G1: Producto | H1: Unidades | I1: Precio_Unitario | J1: Costo_Unitario | K1: Ventas_Origen
A2: 1724 | B2: 45835 | C2: Centro | D2: Cordoba | E2: e-commerce | F2: computación | G2: Monitor 4K 27 | H2: 10 | I2: 433.15 | J2: 280.42 | K2: =IF(ISTEXT(H2),VALUE(H2),H2)*I2 -> 4331.5 | N2: EXPORT CRUDO · NO EDITAR · entrada del proceso
A3: 639 | B3: 45492 | C3: Centro | D3: Cordoba | E3: Tienda fisica | F3: Almacenamiento | G3: Pendrive 256GB | H3: 30 | I3: 34.3 | J3: 17.85 | K3: =IF(ISTEXT(H3),VALUE(H3),H3)*I3 -> 1029
A4: 8 | B4: 03/01/2024 | C4: A.M.B.A. | D4: Buenos Aires | E4: E-COMMERCE | F4: accesorios | G4: Mouse Inalambrico | H4: 30 | I4: 27.44 | J4: 13.44 | K4: =IF(ISTEXT(H4),VALUE(H4),H4)*I4 -> 823.2 | N4: Que es esta hoja
A5: 1807 | B5: 45852 | C5: A.M.B.A. | D5: Buenos Aires | E5: TIENDA FISICA | F5: Accesorios | G5: Mouse Inalambrico | H5: 95 | I5: 28.11 | J5: 13.84 | K5: =IF(ISTEXT(H5),VALUE(H5),H5)*I5 -> 2670.45 | N5: El archivo tal como lo entrega el sistema transaccional. Se deja intacto a proposito: es la evidencia de que la limpieza se hizo y permite rehacerla si cambia una regla.
A6: 1511 | B6: 45768 | C6: A.M.B.A. | D6: Buenos Aires | E6: Tienda fisica | F6: Accesorios | G6: Webcam Full HD | H6: 86 | I6: 64.58 | J6: 36.49 | K6: =IF(ISTEXT(H6),VALUE(H6),H6)*I6 -> 5553.88
A7: 836 | B7: 21/09/2024 | C7: Centro | D7: Cordoba | E7: E-commerce | F7: Audio | G7: Parlante Bluetooth | H7: 12 | I7: 83.3 | J7: 48.03 | K7: =IF(ISTEXT(H7),VALUE(H7),H7)*I7 -> 999.6
A8: 1355 | B8: 45697 | C8: LITORAL | D8: Rosario | E8: tienda fisica | F8: Audio | G8: Parlante Bluetooth | H8: 15 | I8: 84.46 | J8: 49.47 | K8: =IF(ISTEXT(H8),VALUE(H8),H8)*I8 -> 1266.9
A9: 1387 | B9: 45705 | C9: NOA | D9: Tucuman | E9: tienda fisica | F9: Accesorios | G9: Mouse Inalambrico | H9: 25 | I9: 27.82 | J9: 13.84 | K9: =IF(ISTEXT(H9),VALUE(H9),H9)*I9 -> 695.5 | N9: Las celdas ambar
A10: 516 | B10: 45465 | C10: AMBA | D10: Buenos Aires | E10: E-commerce | F10: AUDIO | G10: Parlante Bluetooth | H10: 17 | I10: 83.3 | J10: 48.03 | K10: =IF(ISTEXT(H10),VALUE(H10),H10)*I10 -> 1416.1 | N10: Estan resaltadas por formato condicional. Marcan los cuatro defectos: ID repetido, fecha cargada como texto, unidades cargadas como texto y ciudad vacia.
A11: 1948 | B11: 45871 | C11: Litoral | D11: Rosario | E11: Ecommerce | F11: Accesorios | G11: Mouse Inalambrico | H11: 25 | I11: 28.11 | J11: 13.84 | K11: =IF(ISTEXT(H11),VALUE(H11),H11)*I11 -> 702.75
A12: 1223 | B12: 45660 | C12: CENTRO | D12: Cordoba | E12: Tienda Fisica | F12: Computacion | G12: Monitor 4K 27 | H12: 9 | I12: 433.15 | J12: 280.42 | K12: =IF(ISTEXT(H12),VALUE(H12),H12)*I12 -> 3898.35
A13: 808 | B13: 14/09/2024 | C13: AMBA | D13: Buenos Aires | E13: E-commerce | F13: accesorios | G13: Mouse Inalambrico | H13: 45 | I13: 27.44 | J13: 13.44 | K13: =IF(ISTEXT(H13),VALUE(H13),H13)*I13 -> 1234.8
A14: 1058 | B14: 09/11/2024 | C14: LITORAL | D14: Rosario | E14: E-COMMERCE | F14: Almacenamiento | G14: SSD Externo 1TB | H14: 13 | I14: 127.4 | J14: 76.05 | K14: =IF(ISTEXT(H14),VALUE(H14),H14)*I14 -> 1656.2 | N14: Los textos sin estandarizar
A15: 1757 | B15: 2025-06-15 | C15: Litoral | D15: Rosario | E15: TIENDA FISICA | F15: Almacenamiento | G15: SSD Externo 1TB | H15: 24 | I15: 129.17 | J15: 78.33 | K15: =IF(ISTEXT(H15),VALUE(H15),H15)*I15 -> 3100.08 | N15: Region, Canal y Categoria llegan con mayusculas, minusculas, acentos y espacios mezclados. El diccionario de la hoja Parametros los unifica.
A16: 1383 | B16: 16/02/2025 | C16: Noa | E16: Tienda física | F16: Computación | G16: Monitor 4K 27 | H16: 6 | I16: 433.15 | J16: 280.42 | K16: =IF(ISTEXT(H16),VALUE(H16),H16)*I16 -> 2598.9
A17: 1261 | B17: 45683 | C17: Cuyo | D17: Mendoza | E17: Tienda fisica | F17: COMPUTACION | G17: Laptop Pro 15 | H17: 6 | I17: 1155.06 | J17: 766.32 | K17: =IF(ISTEXT(H17),VALUE(H17),H17)*I17 -> 6930.36
A18: 206 | B18: 2024-03-12 | C18: A.M.B.A. | D18: Buenos Aires | E18: Ecommerce | F18: computación | G18: PC Gamer Ryzen | H18: 8 | I18: 1617 | J18: 1122 | K18: =IF(ISTEXT(H18),VALUE(H18),H18)*I18 -> 12936
A19: 2192 | B19: 45939 | C19: noa | D19: Tucuman | E19: E-commerce | F19: ACCESORIOS | G19: Webcam Full HD | H19: 22 | I19: 65.26 | J19: 36.49 | K19: =IF(ISTEXT(H19),VALUE(H19),H19)*I19 -> 1435.72 | N19: Que pasa despues
A20: 1083 | B20: 22/11/2024 | C20: NOA | D20: Tucuman | E20: Tienda fisica | F20: Computacion | G20: Monitor 4K 27 | H20: 8 | I20: 441 | J20: 272.25 | K20: =IF(ISTEXT(H20),VALUE(H20),H20)*I20 -> 3528 | N20: La hoja Datos_Limpios reconstruye cada fila con formulas y la hoja Control_Calidad verifica que no quede ningun defecto.
A21: 101 | B21: 45328 | C21: amba | D21: Buenos Aires | E21: Tienda fisica | F21: Computación | G21: Laptop Pro 15 | H21: 18 | I21: 1176 | J21: 744 | K21: =IF(ISTEXT(H21),VALUE(H21),H21)*I21 -> 21168
A22: 641 | B22: 45479 | C22: litoral | D22: Rosario | E22: TIENDA FISICA | F22: computacion | G22: Laptop Pro 15 | H22: 10 | I22: 1176 | J22: 744 | K22: =IF(ISTEXT(H22),VALUE(H22),H22)*I22 -> 11760
A23: 749 | B23: 45510 | C23: Litoral | D23: Rosario | E23: TIENDA FISICA | F23: ACCESORIOS | G23: Teclado Mecanico | H23: 33 | I23: 93.1 | J23: 47.98 | K23: =IF(ISTEXT(H23),VALUE(H23),H23)*I23 -> 3072.3
A24: 2024 | B24: 45921 | C24: Centro | D24: Cordoba | E24: E-commerce | F24: Computacion | G24: Monitor 4K 27 | H24: 9 | I24: 451.78 | J24: 280.42 | K24: =IF(ISTEXT(H24),VALUE(H24),H24)*I24 -> 4066.02
A25: 1229 | B25: 45675 | C25: Centro | D25: Cordoba | E25: Tienda fisica | F25: accesorios | G25: Teclado Mecanico | H25: 39 | I25: 94.39 | J25: 49.41 | K25: =IF(ISTEXT(H25),VALUE(H25),H25)*I25 -> 3681.21
A26: 954 | B26: 45575 | C26: Litoral | D26: Rosario | E26: e-commerce | F26: AUDIO | G26: Auriculares BT Pro | H26: 7 | I26: 117.6 | J26: 63.6 | K26: =IF(ISTEXT(H26),VALUE(H26),H26)*I26 -> 823.2
A27: 2306 | B27: 46015 | C27: AMBA | D27: Buenos Aires | E27: e-commerce | F27: computación | G27: PC Gamer Ryzen | H27: 21 | I27: 1656.52 | J27: 1155.66 | K27: =IF(ISTEXT(H27),VALUE(H27),H27)*I27 -> 34786.92
A28: 1821 | B28: 04/07/2025 | C28: centro | D28: Cordoba | E28: Tienda fisica | F28: COMPUTACION | G28: Laptop Pro 15 | H28: 14 | I28: 1204.74 | J28: 766.32 | K28: =IF(ISTEXT(H28),VALUE(H28),H28)*I28 -> 16866.36
A29: 1394 | B29: 12/02/2025 | C29: NOA | D29: Tucuman | E29: E-commerce | F29: audio | G29: Auriculares BT Pro | H29: 7 | I29: 119.23 | J29: 65.51 | K29: =IF(ISTEXT(H29),VALUE(H29),H29)*I29 -> 834.61
A30: 23 | B30: 27/01/2024 | C30: Centro | D30: Cordoba | E30: Tienda física | F30: Computación | G30: Monitor 4K 27 | H30: 9 | I30: 441 | J30: 272.25 | K30: =IF(ISTEXT(H30),VALUE(H30),H30)*I30 -> 3969
A31: 2249 | B31: 45964 | C31: litoral | D31: Rosario | E31: TIENDA FISICA | F31: Accesorios | G31: Teclado Mecanico | H31: 45 | I31: 95.38 | J31: 49.41 | K31: =IF(ISTEXT(H31),VALUE(H31),H31)*I31 -> 4292.1
A32: 922 | B32: 45567 | C32: Centro | D32: Cordoba | E32: e-commerce | F32: Computacion | G32: Laptop Pro 15 | H32: 5 | I32: 1176 | J32: 744 | K32: =IF(ISTEXT(H32),VALUE(H32),H32)*I32 -> 5880
A33: 857 | B33: 06/09/2024 | C33: litoral | D33: Rosario | E33: tienda fisica | F33: Almacenamiento | G33: SSD Externo 1TB | H33: 21 | I33: 127.4 | J33: 76.05 | K33: =IF(ISTEXT(H33),VALUE(H33),H33)*I33 -> 2675.4
A34: 1695 | B34: 13/05/2025 | C34: noa | D34: Tucuman | E34: TIENDA FISICA | F34: Audio | G34: Parlante Bluetooth | H34: 13 | I34: 84.46 | J34: 49.47 | K34: =IF(ISTEXT(H34),VALUE(H34),H34)*I34 -> 1097.98
A35: 843 | B35: 16/09/2024 | C35: Litoral | E35: Tienda fisica | F35: computación | G35: Monitor 4K 27 | H35: 10 | I35: 441 | J35: 272.25 | K35: =IF(ISTEXT(H35),VALUE(H35),H35)*I35 -> 4410
A36: 798 | B36: 45529 | C36: noa | D36: Tucuman | E36: E-COMMERCE | F36: ALMACENAMIENTO | G36: SSD Externo 1TB | H36: 8 | I36: 127.4 | J36: 76.05 | K36: =IF(ISTEXT(H36),VALUE(H36),H36)*I36 -> 1019.2
A37: 2141 | B37: 45933 | C37: LITORAL | D37: Rosario | E37: Tienda fisica | F37: Computación | G37: Laptop Pro 15 | H37: 8 | I37: 1204.74 | J37: 766.32 | K37: =IF(ISTEXT(H37),VALUE(H37),H37)*I37 -> 9637.92
A38: 113 | B38: 2024-02-09 | C38: Amba | D38: Buenos Aires | E38: Tienda Fisica | F38: Audio | G38: Auriculares BT Pro | H38: 40 | I38: 117.6 | J38: 63.6 | K38: =IF(ISTEXT(H38),VALUE(H38),H38)*I38 -> 4704
A39: 830 | B39: 45541 | C39: Centro | D39: Cordoba | E39: E-commerce | F39: accesorios | G39: Teclado Mecanico | H39: 26 | I39: 93.1 | J39: 47.98 | K39: =IF(ISTEXT(H39),VALUE(H39),H39)*I39 -> 2420.6
A40: 1924 | B40: 2025-08-23 | C40: Centro | D40: Cordoba | E40: E-commerce | F40: Computacion | G40: Monitor 4K 27 | H40: 8 | I40: 451.78 | J40: 280.42 | K40: =IF(ISTEXT(H40),VALUE(H40),H40)*I40 -> 3614.24
A41: 1087 | B41: 45619 | C41: NOA | D41: Tucuman | E41: Tienda física | F41: Accesorios | G41: Mouse Inalambrico | H41: 42 | I41: 27.44 | J41: 13.44 | K41: =IF(ISTEXT(H41),VALUE(H41),H41)*I41 -> 1152.48
A42: 593 | B42: 21/06/2024 | C42: noa | D42: Tucuman | E42: Tienda fisica | F42: Audio | G42: Auriculares BT Pro | H42: 15 | I42: 117.6 | J42: 63.6 | K42: =IF(ISTEXT(H42),VALUE(H42),H42)*I42 -> 1764
A43: 414 | B43: 45422 | C43: AMBA | D43: Buenos Aires | E43: Ecommerce | F43: Audio | G43: Auriculares BT Pro | H43: 15 | I43: 117.6 | J43: 63.6 | K43: =IF(ISTEXT(H43),VALUE(H43),H43)*I43 -> 1764
A44: 123 | B44: 25/02/2024 | C44: Centro | D44: Cordoba | E44: TIENDA FISICA | F44: Computacion | G44: Monitor 4K 27 | H44: 9 | I44: 441 | J44: 272.25 | K44: =IF(ISTEXT(H44),VALUE(H44),H44)*I44 -> 3969
A45: 1278 | B45: 45667 | C45: Cuyo | E45: E-commerce | F45: Almacenamiento | G45: SSD Externo 1TB | H45: 11 | I45: 129.17 | J45: 78.33 | K45: =IF(ISTEXT(H45),VALUE(H45),H45)*I45 -> 1420.87
A46: 1923 | B46: 45885 | C46: Centro | D46: Cordoba | E46: Tienda física | F46: computacion | G46: Monitor 4K 27 | H46: 10 | I46: 451.78 | J46: 280.42 | K46: =IF(ISTEXT(H46),VALUE(H46),H46)*I46 -> 4517.8
A47: 233 | B47: 45363 | C47: Centro | D47: Cordoba | E47: Tienda fisica | F47: Audio | G47: Auriculares BT Pro | H47: 23 | I47: 117.6 | J47: 63.6 | K47: =IF(ISTEXT(H47),VALUE(H47),H47)*I47 -> 2704.8
A48: 1904 | B48: 45887 | C48: A.M.B.A. | D48: Buenos Aires | E48: Ecommerce | F48: COMPUTACION | G48: Monitor 4K 27 | H48: 12 | I48: 451.78 | J48: 280.42 | K48: =IF(ISTEXT(H48),VALUE(H48),H48)*I48 -> 5421.36
A49: 959 | B49: 45583 | C49: litoral | D49: Rosario | E49: Tienda Fisica | F49: Almacenamiento | G49: Pendrive 256GB | H49: 24 | I49: 34.3 | J49: 17.85 | K49: =IF(ISTEXT(H49),VALUE(H49),H49)*I49 -> 823.2
A50: 635 | B50: 45491 | C50: CENTRO | E50: tienda fisica | F50: AUDIO | G50: Parlante Bluetooth | H50: 25 | I50: 83.3 | J50: 48.03 | K50: =IF(ISTEXT(H50),VALUE(H50),H50)*I50 -> 2082.5
A51: 353 | B51: 15/04/2024 | C51: LITORAL | D51: Rosario | E51: Tienda fisica | F51: audio | G51: Auriculares BT Pro | H51: 18 | I51: 117.6 | J51: 63.6 | K51: =IF(ISTEXT(H51),VALUE(H51),H51)*I51 -> 2116.8
A52: 495 | B52: 10/05/2024 | C52: noa | D52: Tucuman | E52: tienda fisica | F52: Audio | G52: Parlante Bluetooth | H52: 12 | I52: 83.3 | J52: 48.03 | K52: =IF(ISTEXT(H52),VALUE(H52),H52)*I52 -> 999.6
A53: 202 | B53: 45362 | C53: AMBA | D53: Buenos Aires | E53: E commerce | F53: computación | G53: Laptop Pro 15 | H53: 8 | I53: 1176 | J53: 744 | K53: =IF(ISTEXT(H53),VALUE(H53),H53)*I53 -> 9408
A54: 838 | B54: 08/09/2024 | C54: centro | D54: Cordoba | E54: Ecommerce | F54: Almacenamiento | G54: SSD Externo 1TB | H54: 13 | I54: 127.4 | J54: 76.05 | K54: =IF(ISTEXT(H54),VALUE(H54),H54)*I54 -> 1656.2
A55: 1573 | B55: 45770 | C55: Cuyo | D55: Mendoza | E55: tienda fisica | F55: AUDIO | G55: Auriculares BT Pro | H55: 13 | I55: 119.23 | J55: 65.51 | K55: =IF(ISTEXT(H55),VALUE(H55),H55)*I55 -> 1549.99
A56: 91 | B56: 45308 | C56: NOA | D56: Tucuman | E56: TIENDA FISICA | F56: accesorios | G56: Webcam Full HD | H56: 25 | I56: 63.7 | J56: 35.43 | K56: =IF(ISTEXT(H56),VALUE(H56),H56)*I56 -> 1592.5
A57: 1000 | B57: 45573 | C57: NOA | D57: Tucuman | E57: e-commerce | F57: almacenamiento | G57: Pendrive 256GB | H57: 8 | I57: 34.3 | J57: 17.85 | K57: =IF(ISTEXT(H57),VALUE(H57),H57)*I57 -> 274.4
A58: 2187 | B58: 45931 | C58: noa | E58: Tienda fisica | F58: Accesorios | G58: Mouse Inalambrico | H58: 36 | I58: 28.11 | J58: 13.84 | K58: =IF(ISTEXT(H58),VALUE(H58),H58)*I58 -> 1011.96
A59: 1750 | B59: 45828 | C59: LITORAL | D59: Rosario | E59: E-commerce | F59: Accesorios | G59: Teclado Mecanico | H59: 24 | I59: 94.39 | J59: 49.41 | K59: =IF(ISTEXT(H59),VALUE(H59),H59)*I59 -> 2265.36
A60: 1495 | B60: 45733 | C60: NOA | D60: Tucuman | E60: Tienda Fisica | F60: AUDIO | G60: Parlante Bluetooth | H60: 13 | I60: 84.46 | J60: 49.47 | K60: =IF(ISTEXT(H60),VALUE(H60),H60)*I60 -> 1097.98
A61: 1870 | B61: 45861 | C61: CUYO | E61: E-commerce | F61: accesorios | G61: Teclado Mecanico | H61: 24 | I61: 95.38 | J61: 49.41 | K61: =IF(ISTEXT(H61),VALUE(H61),H61)*I61 -> 2289.12
A62: 892 | B62: 45543 | C62: NOA | D62: Tucuman | E62: E commerce | F62: ACCESORIOS | G62: Webcam Full HD | H62: 14 | I62: 63.7 | J62: 35.43 | K62: =IF(ISTEXT(H62),VALUE(H62),H62)*I62 -> 891.8
A63: 846 | B63: 45545 | C63: Litoral | D63: Rosario | E63: E commerce | F63: computacion | G63: PC Gamer Ryzen | H63: 3 | I63: 1617 | J63: 1122 | K63: =IF(ISTEXT(H63),VALUE(H63),H63)*I63 -> 4851
A64: 1844 | B64: 03/07/2025 | C64: LITORAL | D64: Rosario | E64: E commerce | F64: Computación | G64: Monitor 4K 27 | H64: 7 | I64: 451.78 | J64: 280.42 | K64: =IF(ISTEXT(H64),VALUE(H64),H64)*I64 -> 3162.46
A65: 1266 | B65: 07/01/2025 | C65: CUYO | D65: Mendoza | E65: E commerce | F65: computación | G65: PC Gamer Ryzen | H65: 4 | I65: 1588.21 | J65: 1155.66 | K65: =IF(ISTEXT(H65),VALUE(H65),H65)*I65 -> 6352.84
A66: 1554 | B66: 45772 | C66: litoral | D66: Rosario | E66: E-commerce | F66: AUDIO | G66: Auriculares BT Pro | H66: 12 | I66: 119.23 | J66: 65.51 | K66: =IF(ISTEXT(H66),VALUE(H66),H66)*I66 -> 1430.76
A67: 35 | B67: 2024-01-03 | C67: Centro | D67: Cordoba | E67: Tienda física | F67: Audio | G67: Parlante Bluetooth | H67: 20 | I67: 83.3 | J67: 48.03 | K67: =IF(ISTEXT(H67),VALUE(H67),H67)*I67 -> 1666
A68: 825 | B68: 2024-09-25 | C68: Centro | D68: Cordoba | E68: Tienda Fisica | F68: COMPUTACION | G68: PC Gamer Ryzen | H68: 11 | I68: 1617 | J68: 1122 | K68: =IF(ISTEXT(H68),VALUE(H68),H68)*I68 -> 17787
A69: 1781 | B69: 45829 | C69: NOA | D69: Tucuman | E69: tienda fisica | F69: Computacion | G69: Laptop Pro 15 | H69: 8 | I69: 1155.06 | J69: 766.32 | K69: =IF(ISTEXT(H69),VALUE(H69),H69)*I69 -> 9240.48
A70: 579 | B70: 45447 | C70: Cuyo | D70: Mendoza | E70: Tienda fisica | F70: Almacenamiento | G70: Pendrive 256GB | H70: 18 | I70: 34.3 | J70: 17.85 | K70: =IF(ISTEXT(H70),VALUE(H70),H70)*I70 -> 617.4
A71: 714 | B71: 04/08/2024 | C71: Amba | D71: Buenos Aires | E71: E commerce | F71: AUDIO | G71: Auriculares BT Pro | H71: 19 | I71: 117.6 | J71: 63.6 | K71: =IF(ISTEXT(H71),VALUE(H71),H71)*I71 -> 2234.4
A72: 504 | B72: 45462 | C72: AMBA | D72: Buenos Aires | E72: E-commerce | F72: computacion | G72: Monitor 4K 27 | H72: 10 | I72: 441 | J72: 272.25 | K72: =IF(ISTEXT(H72),VALUE(H72),H72)*I72 -> 4410
A73: 2127 | B73: 2025-10-13 | C73: Centro | D73: Cordoba | E73: Tienda física | F73: Accesorios | G73: Mouse Inalambrico | H73: 55 | I73: 28.11 | J73: 13.84 | K73: =IF(ISTEXT(H73),VALUE(H73),H73)*I73 -> 1546.05
A74: 1655 | B74: 03/05/2025 | C74: litoral | D74: Rosario | E74: Tienda fisica | F74: audio | G74: Parlante Bluetooth | H74: 20 | I74: 84.46 | J74: 49.47 | K74: =IF(ISTEXT(H74),VALUE(H74),H74)*I74 -> 1689.2
A75: 1173 | B75: 04/12/2024 | C75: cuyo | D75: Mendoza | E75: Tienda Fisica | F75: Audio | G75: Auriculares BT Pro | H75: 18 | I75: 117.6 | J75: 63.6 | K75: =IF(ISTEXT(H75),VALUE(H75),H75)*I75 -> 2116.8
A76: 998 | B76: 21/10/2024 | C76: NOA | D76: Tucuman | E76: e-commerce | F76: Almacenamiento | G76: SSD Externo 1TB | H76: 8 | I76: 127.4 | J76: 76.05 | K76: =IF(ISTEXT(H76),VALUE(H76),H76)*I76 -> 1019.2
A77: 2380 | B77: 02/12/2025 | C77: CUYO | D77: Mendoza | E77: E-COMMERCE | F77: Almacenamiento | G77: Pendrive 256GB | H77: 15 | I77: 35.14 | J77: 18.39 | K77: =IF(ISTEXT(H77),VALUE(H77),H77)*I77 -> 527.1
A78: 1822 | B78: 45849 | C78: CENTRO | D78: Cordoba | E78: E-commerce | F78: Computación | G78: Laptop Pro 15 | H78: 8 | I78: 1204.74 | J78: 766.32 | K78: =IF(ISTEXT(H78),VALUE(H78),H78)*I78 -> 9637.92
A79: 2083 | B79: 45902 | C79: Noa | D79: Tucuman | E79: Tienda fisica | F79: computacion | G79: Monitor 4K 27 | H79: 6 | I79: 451.78 | J79: 280.42 | K79: =IF(ISTEXT(H79),VALUE(H79),H79)*I79 -> 2710.68
A80: 231 | B80: 45376 | C80: Centro | D80: Cordoba | E80: Tienda fisica | F80: accesorios | G80: Webcam Full HD | H80: 56 | I80: 63.7 | J80: 35.43 | K80: =IF(ISTEXT(H80),VALUE(H80),H80)*I80 -> 3567.2
A81: 1095 | B81: 25/11/2024 | C81: NOA | D81: Tucuman | E81: tienda fisica | F81: Audio | G81: Parlante Bluetooth | H81: 15 | I81: 83.3 | J81: 48.03 | K81: =IF(ISTEXT(H81),VALUE(H81),H81)*I81 -> 1249.5
A82: 564 | B82: 07/06/2024 | C82: Cuyo | D82: Mendoza | E82: Ecommerce | F82: Computacion | G82: Monitor 4K 27 | H82: 3 | I82: 441 | J82: 272.25 | K82: =IF(ISTEXT(H82),VALUE(H82),H82)*I82 -> 1323
A83: 312 | B83: 25/04/2024 | C83: Amba | D83: Buenos Aires | E83: E-commerce | F83: accesorios | G83: Webcam Full HD | H83: 37 | I83: 63.7 | J83: 35.43 | K83: =IF(ISTEXT(H83),VALUE(H83),H83)*I83 -> 2356.9
A84: 1683 | B84: 10/05/2025 | C84: NOA | D84: Tucuman | E84: tienda fisica | F84: Computación | G84: Monitor 4K 27 | H84: 6 | I84: 433.15 | J84: 280.42 | K84: =IF(ISTEXT(H84),VALUE(H84),H84)*I84 -> 2598.9
A85: 430 | B85: 45426 | C85: centro | D85: Cordoba | E85: Ecommerce | F85: Accesorios | G85: Teclado Mecanico | H85: 21 | I85: 93.1 | J85: 47.98 | K85: =IF(ISTEXT(H85),VALUE(H85),H85)*I85 -> 1955.1
A86: 362 | B86: 24/04/2024 | C86: CUYO | D86: Mendoza | E86: E-commerce | F86: computación | G86: Laptop Pro 15 | H86: 2 | I86: 1176 | J86: 744 | K86: =IF(ISTEXT(H86),VALUE(H86),H86)*I86 -> 2352
A87: 602 | B87: 45476 | C87: AMBA | D87: Buenos Aires | E87: Ecommerce | F87: Computacion | G87: Laptop Pro 15 | H87: 10 | I87: 1176 | J87: 744 | K87: =IF(ISTEXT(H87),VALUE(H87),H87)*I87 -> 11760
A88: 525 | B88: 45447 | C88: Centro | D88: Cordoba | E88: Tienda Fisica | F88: COMPUTACION | G88: PC Gamer Ryzen | H88: 11 | I88: 1617 | J88: 1122 | K88: =IF(ISTEXT(H88),VALUE(H88),H88)*I88 -> 17787
A89: 1503 | B89: 45766 | C89: AMBA | D89: Buenos Aires | E89: tienda fisica | F89: computacion | G89: Monitor 4K 27 | H89: 16 | I89: 433.15 | J89: 280.42 | K89: =IF(ISTEXT(H89),VALUE(H89),H89)*I89 -> 6930.4
A90: 351 | B90: 45383 | C90: litoral | D90: Rosario | E90: Tienda fisica | F90: ACCESORIOS | G90: Webcam Full HD | H90: 38 | I90: 63.7 | J90: 35.43 | K90: =IF(ISTEXT(H90),VALUE(H90),H90)*I90 -> 2420.6
A91: 1240 | B91: 2025-01-14 | C91: CENTRO | D91: Cordoba | E91: E-commerce | F91: Almacenamiento | G91: Pendrive 256GB | H91: 19 | I91: 34.78 | J91: 18.39 | K91: =IF(ISTEXT(H91),VALUE(H91),H91)*I91 -> 660.82
A92: 957 | B92: 04/10/2024 | C92: litoral | D92: Rosario | E92: Tienda Fisica | F92: Almacenamiento | G92: SSD Externo 1TB | H92: 26 | I92: 127.4 | J92: 76.05 | K92: =IF(ISTEXT(H92),VALUE(H92),H92)*I92 -> 3312.4
A93: 1096 | B93: 45601 | C93: noa | D93: Tucuman | E93: E-commerce | F93: Audio | G93: Parlante Bluetooth | H93: 7 | I93: 83.3 | J93: 48.03 | K93: =IF(ISTEXT(H93),VALUE(H93),H93)*I93 -> 583.1
A94: 1535 | B94: 27/04/2025 | C94: centro | D94: Cordoba | E94: Tienda fisica | F94: Audio | G94: Parlante Bluetooth | H94: 21 | I94: 84.46 | J94: 49.47 | K94: =IF(ISTEXT(H94),VALUE(H94),H94)*I94 -> 1773.66
A95: 1556 | B95: 12/04/2025 | C95: LITORAL | D95: Rosario | E95: Ecommerce | F95: AUDIO | G95: Parlante Bluetooth | H95: 11 | I95: 84.46 | J95: 49.47 | K95: =IF(ISTEXT(H95),VALUE(H95),H95)*I95 -> 929.06
A96: 559 | B96: 45469 | C96: Litoral | D96: Rosario | E96: Tienda física | F96: almacenamiento | G96: Pendrive 256GB | H96: 26 | I96: 34.3 | J96: 17.85 | K96: =IF(ISTEXT(H96),VALUE(H96),H96)*I96 -> 891.8
A97: 626 | B97: 45482 | C97: Centro | D97: Cordoba | E97: E commerce | F97: Computacion | G97: PC Gamer Ryzen | H97: 6 | I97: 1617 | J97: 1122 | K97: =IF(ISTEXT(H97),VALUE(H97),H97)*I97 -> 9702
A98: 752 | B98: 45531 | C98: Litoral | E98: E-commerce | F98: ACCESORIOS | G98: Webcam Full HD | H98: 16 | I98: 63.7 | J98: 35.43 | K98: =IF(ISTEXT(H98),VALUE(H98),H98)*I98 -> 1019.2
A99: 222 | B99: 45367 | C99: Centro | D99: Cordoba | E99: E commerce | F99: computación | G99: Laptop Pro 15 | H99: 4 | I99: 1176 | J99: 744 | K99: =IF(ISTEXT(H99),VALUE(H99),H99)*I99 -> 4704
A100: 1674 | B100: 2025-05-01 | C100: CUYO | D100: Mendoza | E100: E-COMMERCE | F100: Audio | G100: Auriculares BT Pro | H100: 10 | I100: 119.23 | J100: 65.51 | K100: =IF(ISTEXT(H100),VALUE(H100),H100)*I100 -> 1192.3
...

Sheet Control_Calidad
B2: Control de calidad del dato
B3: Cada fila mide un defecto del export crudo y verifica que despues del ETL ya no exista. Todos los numeros son formulas sobre las hojas Datos_Origen y Datos_Limpios: si el origen cambia, este tablero se actualiza solo. Nota: CONTAR.SI no distingue mayusculas de minusculas, asi que las cuentas de valores distintos son un piso; el diccionario de Parametros publica todas las variantes recibidas, una por fila.
B6: DIAGNOSTICO Y REMEDIACION
B7: Problema de calidad | C7: Regla aplicada | D7: En el origen | E7: Despues del ETL | F7: Estado
B8: Registros duplicados | C8: Se conserva la primera aparicion de cada ID_Venta y se descartan los reenvios del sistema. | D8: =2458-SUMPRODUCT((Datos_Origen!$A$2:$A$2459<>"")/COUNTIF(Datos_Origen!$A$2:$A$2459,Datos_Origen!$A$2:$A$2459&"")) -> 58 | E8: =2400-SUMPRODUCT((Datos_Limpios!$A$2:$A$2401<>"")/COUNTIF(Datos_Limpios!$A$2:$A$2401,Datos_Limpios!$A$2:$A$2401&"")) -> 0 | F8: =IF(E8=0,"OK","REVISAR") -> OK
B9: Fechas almacenadas como texto | C9: Se detecta el formato (dd/mm/aaaa o aaaa-mm-dd) y se reconstruye la fecha real con FECHA/DATE. | D9: =SUMPRODUCT(--ISTEXT(Datos_Origen!$B$2:$B$2459)) -> 845 | E9: =SUMPRODUCT(--ISTEXT(Datos_Limpios!$B$2:$B$2401)) -> 0 | F9: =IF(E9=0,"OK","REVISAR") -> OK
B10: Unidades cargadas como texto | C10: Se convierten a numero con VALOR/VALUE solo cuando la celda es texto. | D10: =SUMPRODUCT(--ISTEXT(Datos_Origen!$H$2:$H$2459)) -> 246 | E10: =SUMPRODUCT(--ISTEXT(Datos_Limpios!$O$2:$O$2401)) -> 0 | F10: =IF(E10=0,"OK","REVISAR") -> OK
B11: Ciudades vacias | C11: Se completan con la ciudad de referencia de la region (INDICE/COINCIDIR contra Parametros). | D11: =COUNTBLANK(Datos_Origen!$D$2:$D$2459) -> 159 | E11: =COUNTBLANK(Datos_Limpios!$I$2:$I$2401) -> 0 | F11: =IF(E11=0,"OK","REVISAR") -> OK
B12: Valores distintos en Categoria | C12: Diccionario de normalizacion: cada variante recibida se mapea a un unico valor estandar. Deben quedar tantos valores como categorias reales. | D12: =SUMPRODUCT((Datos_Origen!$F$2:$F$2459<>"")/COUNTIF(Datos_Origen!$F$2:$F$2459,Datos_Origen!$F$2:$F$2459&"")) -> 11 | E12: =SUMPRODUCT((Datos_Limpios!$K$2:$K$2401<>"")/COUNTIF(Datos_Limpios!$K$2:$K$2401,Datos_Limpios!$K$2:$K$2401&"")) -> 4 | F12: =IF(E12=4,"OK","REVISAR") -> OK
B13: Valores distintos en Region | C13: Mismo diccionario, dimension Region. | D13: =SUMPRODUCT((Datos_Origen!$C$2:$C$2459<>"")/COUNTIF(Datos_Origen!$C$2:$C$2459,Datos_Origen!$C$2:$C$2459&"")) -> 11 | E13: =SUMPRODUCT((Datos_Limpios!$H$2:$H$2401<>"")/COUNTIF(Datos_Limpios!$H$2:$H$2401,Datos_Limpios!$H$2:$H$2401&"")) -> 5 | F13: =IF(E13=5,"OK","REVISAR") -> OK
B14: Valores distintos en Canal | C14: Mismo diccionario, dimension Canal. | D14: =SUMPRODUCT((Datos_Origen!$E$2:$E$2459<>"")/COUNTIF(Datos_Origen!$E$2:$E$2459,Datos_Origen!$E$2:$E$2459&"")) -> 7 | E14: =SUMPRODUCT((Datos_Limpios!$J$2:$J$2401<>"")/COUNTIF(Datos_Limpios!$J$2:$J$2401,Datos_Limpios!$J$2:$J$2401&"")) -> 2 | F14: =IF(E14=2,"OK","REVISAR") -> OK
B15: Valores distintos en Producto | C15: ESPACIOS/TRIM sobre el nombre recibido. | D15: =SUMPRODUCT((Datos_Origen!$G$2:$G$2459<>"")/COUNTIF(Datos_Origen!$G$2:$G$2459,Datos_Origen!$G$2:$G$2459&"")) -> 30 | E15: =SUMPRODUCT((Datos_Limpios!$M$2:$M$2401<>"")/COUNTIF(Datos_Limpios!$M$2:$M$2401,Datos_Limpios!$M$2:$M$2401&"")) -> 10 | F15: =IF(E15=10,"OK","REVISAR") -> OK
B17: RECONCILIACION
B18: Concepto | C18: Detalle | D18: Valor
B19: Filas recibidas en el export | C19: Todo lo que entrego el sistema, reenvios incluidos. | D19: =COUNTA(Datos_Origen!$A$2:$A$2459) -> 2458
B20: Operaciones unicas | C20: Filas distintas por ID_Venta: lo que realmente ocurrio. | D20: =SUMPRODUCT((Datos_Origen!$A$2:$A$2459<>"")/COUNTIF(Datos_Origen!$A$2:$A$2459,Datos_Origen!$A$2:$A$2459&"")) -> 2400
B21: Filas descartadas por duplicado | C21: Diferencia entre las dos anteriores. | D21: =D19-D20 -> 58
B22: Facturacion del export crudo | C22: Unidades x precio sobre TODAS las filas recibidas. | D22: =SUM(Datos_Origen!$K$2:$K$2459) -> 10550977
B23: Facturacion depurada | C23: La misma cuenta sobre la tabla limpia. | D23: =SUM(Datos_Limpios!$R$2:$R$2401) -> 10292360
B24: Facturacion que inflaban los duplicados | C24: Lo que se habria reportado de mas sin depurar. | D24: =D22-D23 -> 258616.33
B25: Filas de la tabla limpia | C25: Debe coincidir con las operaciones unicas. | D25: =COUNTA(Datos_Limpios!$A$2:$A$2401) -> 2400
B26: Control de deduplicacion | C26: Filas donde Pos_Origen NO apunta a la primera aparicion del ID_Venta. Tiene que ser cero. | D26: =COUNTIF(Datos_Limpios!$AA$2:$AA$2401,"REVISAR") -> 0 | E26: =IF(D26=0,"OK","REVISAR") -> OK
B28: COLUMNAS QUE AGREGA EL ETL
B29: Columna calculada | C29: Regla | D29: Resultado
B30: Segmento_Rentabilidad | C30: SI(Y(margen% >= meta; ventas >= ticket alto); "Alta rentabilidad"; SI(O(margen% < piso; ventas < ticket bajo); "Revisar"; "Estandar")) | D30: Alta rentabilidad | E30: =COUNTIF(Datos_Limpios!$W$2:$W$2401,"Alta rentabilidad") -> 521
D31: Estandar | E31: =COUNTIF(Datos_Limpios!$W$2:$W$2401,"Estandar") -> 1655
D32: Revisar | E32: =COUNTIF(Datos_Limpios!$W$2:$W$2401,"Revisar") -> 224
B34: Alerta_Logistica | C34: SI(Y(canal = "E-commerce"; costo logistico / ventas > techo); "Alerta"; "OK") | D34: Alerta | E34: =COUNTIF(Datos_Limpios!$X$2:$X$2401,"Alerta") -> 600
D35: OK | E35: =COUNTIF(Datos_Limpios!$X$2:$X$2401,"OK") -> 1800
B37: Ticket | C37: SI(ventas >= ticket alto; "Alto"; SI(ventas < ticket bajo; "Bajo"; "Medio")) | D37: Alto | E37: =COUNTIF(Datos_Limpios!$Y$2:$Y$2401,"Alto") -> 965
D38: Medio | E38: =COUNTIF(Datos_Limpios!$Y$2:$Y$2401,"Medio") -> 1406
D39: Bajo | E39: =COUNTIF(Datos_Limpios!$Y$2:$Y$2401,"Bajo") -> 29
B42: Las tres columnas anteriores se calculan con logica condicional (SI / Y / O) sobre los umbrales de la hoja Parametros. Cambiar un umbral reclasifica las 2.400 operaciones sin tocar una sola formula.

Sheet Parametros
B2: Parametros, supuestos, metas y diccionarios
B3: Toda constante del modelo vive en esta hoja. El ETL, los KPIs y las columnas logicas la referencian por celda; ninguna la repite escrita a mano. | H3: MESES | K3: LISTAS DE VALIDACION
H4: N | I4: Mes | K4: Region | L4: Categoria | M4: Anio
B5: METAS Y UMBRALES DEL EJERCICIO 2025 | H5: 1 | I5: Ene | K5: AMBA | L5: Computacion | M5: Todos
B6: Indicador | C6: Valor | D6: Se usa en | F6: Origen del supuesto | H6: 2 | I6: Feb | K6: Centro | L6: Accesorios | M6: 2024
B7: Ventas totales 2025 (meta) | C7: 5400000 | D7: KPI 1 | F7: Presupuesto comercial aprobado para el ejercicio. | H7: 3 | I7: Mar | K7: Litoral | L7: Audio | M7: 2025
B8: Margen bruto % (meta) | C8: 0.34 | D8: KPI 2 / columna logica | F8: Piso historico de la cadena: 2024 cerro en 35,8%. | H8: 4 | I8: Abr | K8: Cuyo | L8: Almacenamiento
B9: Crecimiento interanual de ventas (meta) | C9: 0.15 | D9: KPI 3 | F9: Objetivo de expansion fijado por la direccion. | H9: 5 | I9: May | K9: NOA
B10: Costo logistico sobre ventas (techo) | C10: 0.025 | D10: KPI 4 | F10: Techo tolerado a nivel compania; 2024 cerro en 2,18%. | H10: 6 | I10: Jun
B11: Margen bruto % piso por operacion | C11: 0.28 | D11: Columna Segmento_Rentabilidad | F11: Por debajo de este margen la operacion entra en revision comercial. | H11: 7 | I11: Jul | K11: Alimentan las listas desplegables del bloque de consulta de la hoja Tablas_Dinamicas.
B12: Ticket alto (USD) | C12: 3000 | D12: Columnas Segmento_Rentabilidad y Ticket | F12: Corte de venta grande: por encima requiere aprobacion de gerencia. | H12: 8 | I12: Ago
B13: Ticket bajo (USD) | C13: 300 | D13: Columnas Segmento_Rentabilidad y Ticket | F13: Por debajo el costo de atencion se come el margen. | H13: 9 | I13: Sep
B14: Costo logistico / ventas tolerado en e-commerce | C14: 0.05 | D14: Columna Alerta_Logistica | F14: Umbral operativo de la ultima milla en el canal online. | H14: 10 | I14: Oct
B15: Margen bruto % minimo por producto | C15: 0.33 | D15: Grafico de dispersion | F15: Corte que separa la zona de riesgo en el mapa de productos. | H15: 11 | I15: Nov
H16: 12 | I16: Dic
B17: SUPUESTOS DEL DATASET
B18: Periodo cubierto | C18: Ene-2024 a Dic-2025 | F18: Dataset SIMULADO y determinista (semilla fija). Extiende el modelo Ventas_Tech_DB del checkpoint de SQL -mismas categorias, productos y ciudades- a 24 meses, 5 regiones y 2 canales, para poder analizar margen, estacionalidad y evolucion interanual. | H18: CIUDAD POR REGION
B19: Operaciones unicas (tabla de hechos) | C19: 2400 | H19: Region | I19: Ciudad
B20: Aumento de precio de lista 2025 | C20: 0.035 | H20: AMBA | I20: Buenos Aires
B21: Inflacion de costo de compra 2025 | C21: 0.03 | H21: Centro | I21: Cordoba
B22: Crecimiento de unidades 2025 | C22: 0.155 | H22: Litoral | I22: Rosario
B23: Participacion de e-commerce 2024 | C23: 0.28 | H23: Cuyo | I23: Mendoza
B24: Participacion de e-commerce 2025 | C24: 0.41 | H24: NOA | I24: Tucuman
B26: COSTO LOGISTICO SOBRE VENTAS · tasa que aplica el ETL | H26: Se usa para completar las ciudades que el export deja vacias.
B27: Canal | C27: Anio | D27: Trimestre | E27: Tasa
B28: Tienda fisica | C28: 2024 | D28: Q1 | E28: 0.012 | F28: El salto de e-commerce en 2025 (ultima milla y envio bonificado) y su baja en Q3-Q4 al fijar un umbral de envio minimo es el hecho que explica la caida y posterior recuperacion del margen.
B29: Tienda fisica | C29: 2024 | D29: Q2 | E29: 0.012
B30: Tienda fisica | C30: 2024 | D30: Q3 | E30: 0.013
B31: Tienda fisica | C31: 2024 | D31: Q4 | E31: 0.013
B32: Tienda fisica | C32: 2025 | D32: Q1 | E32: 0.013
B33: Tienda fisica | C33: 2025 | D33: Q2 | E33: 0.014
B34: Tienda fisica | C34: 2025 | D34: Q3 | E34: 0.013
B35: Tienda fisica | C35: 2025 | D35: Q4 | E35: 0.013
B36: E-commerce | C36: 2024 | D36: Q1 | E36: 0.042
B37: E-commerce | C37: 2024 | D37: Q2 | E37: 0.044
B38: E-commerce | C38: 2024 | D38: Q3 | E38: 0.046
B39: E-commerce | C39: 2024 | D39: Q4 | E39: 0.048
B40: E-commerce | C40: 2025 | D40: Q1 | E40: 0.068
... B43: E-commerce | C43: 2025 | D43: Q4 | E43: 0.052
B46: DICCIONARIO DE NORMALIZACION DE TEXTO · valor recibido -> valor estandar
B47: CATEGORIA · valor recibido en el export | C47: Valor estandar | F47: Cada fila es una variante que el sistema transaccional devuelve para un mismo valor real. El ETL busca el texto recibido (sin espacios de mas) en la columna izquierda y escribe el estandar de la derecha. Agregar una variante nueva es agregar una fila: no hay que tocar ninguna formula.
B48: Computacion | C48: Computacion
B49: computacion | C49: Computacion
B50: COMPUTACION | C50: Computacion
B51: Computacion | C51: Computacion
B52: Computación | C52: Computacion
B53: computación | C53: Computacion
B54: Accesorios | C54: Accesorios
B55: accesorios | C55: Accesorios
B56: ACCESORIOS | C56: Accesorios
B57: Accesorios | C57: Accesorios
B58: accesorios | C58: Accesorios
B59: Audio | C59: Audio
... B106: E-commerce | C106: E-commerce

Sheet Documentacion
B2: Documentacion del libro
B3: Practica Integradora Final · Coderhouse, Data Analyst · Lleyton Murphy
B5: MAPA DEL LIBRO
B6: Hoja | C6: Rol | D6: Que contiene
B7: Dashboard | C7: El entregable | D7: Titular, 4 tarjetas de KPI, 4 segmentadores, 5 graficos y el reporte ejecutivo. Se abre en esta hoja.
B8: Tablas_Dinamicas | C8: Analisis | D8: Las 4 tablas dinamicas del reporte mas un bloque de consulta con listas desplegables.
B9: Datos_Limpios | C9: Tabla de hechos | D9: 2.400 operaciones depuradas. Cada celda es una formula que reconstruye el valor desde el export crudo.
B10: Datos_Origen | C10: Entrada | D10: El export del sistema transaccional, sin tocar. Los defectos estan resaltados con formato condicional.
B11: Control_Calidad | C11: Auditoria | D11: Cuenta los defectos del origen y verifica con formulas que despues del ETL no quede ninguno.
B12: Parametros | C12: Constantes | D12: Metas, umbrales, tasas, diccionarios de normalizacion y listas de validacion. Ningun numero fijo vive fuera de aca.
B13: Documentacion | C13: Esta hoja | D13: Como esta hecho y como se opera.
B14: Calculos (oculta) | C14: Soporte | D14: Grilla de tamano fijo resuelta con GETPIVOTDATA. Es lo que leen los graficos.
B15: Pivots_Aux (oculta) | C15: Soporte | D15: Tablas dinamicas de una sola medida que alimentan a GETPIVOTDATA.
B17: EL ETL, PASO A PASO · de Datos_Origen a Datos_Limpios
B18: Paso | C18: Funciones usadas | D18: Que hace y por que
B19: 1. Quitar duplicados | C19: COINCIDIR / MATCH | D19: El sistema reenvia lotes y repite filas. Se conserva la primera aparicion de cada ID_Venta. La columna Pos_Origen guarda a que fila del export apunta cada operacion y la columna Control_ETL verifica, fila por fila, que esa sea de verdad la primera aparicion.
B20: 2. Normalizar fechas | C20: SI, ESNUMERO, EXTRAE, FECHA, VALOR | D20: El export mezcla tres formatos: fecha real, texto dd/mm/aaaa y texto aaaa-mm-dd. La formula detecta cual es cada uno y reconstruye una fecha real. Sin esto no hay agrupacion por mes ni por trimestre que funcione.
B21: 3. Estandarizar textos | C21: ESPACIOS, INDICE, COINCIDIR | D21: Region, Canal y Categoria llegan con mayusculas, minusculas, acentos y espacios mezclados. Se resuelven contra el diccionario de la hoja Parametros. Agregar una variante nueva es agregar una fila al diccionario: no hay que tocar ninguna formula.
B22: 4. Corregir tipos | C22: SI, ESTEXTO, VALOR | D22: Algunas unidades llegan como texto. Se convierten a numero solo cuando hace falta, para no romper las que ya venian bien.
B23: 5. Completar vacios | C23: SI, ESPACIOS, INDICE, COINCIDIR | D23: Las ciudades vacias se completan con la ciudad de referencia de la region. Se documenta como imputacion, no se presenta como dato original.
B24: 6. Derivar columnas | C24: ANIO, MES, REDONDEAR.MAS, TEXTO | D24: Anio, Trimestre, Mes, Periodo, Cat_Anio y Prod_Anio salen de la fecha y de los textos ya limpios. Son las que hacen posible el analisis temporal y la comparacion interanual.
B25: 7. Calcular medidas | C25: REDONDEAR, SUMAR.SI.CONJUNTO | D25: Ventas, Costo_Producto, Costo_Logistico y Margen_Bruto se calculan en la planilla, no se pegan como numeros. La tasa logistica no se repite fila a fila: se busca en la tabla de Parametros segun canal, anio y trimestre.
B26: 8. Clasificar | C26: SI, Y, O | D26: Tres columnas de logica condicional: Segmento_Rentabilidad, Alerta_Logistica y Ticket. Son las que convierten un numero en una decision, y son ademas dimensiones de analisis en las tablas dinamicas.
B28: LAS COLUMNAS CALCULADAS CON LOGICA CONDICIONAL
B29: Columna | C29: Regla | D29: Para que sirve
B30: Segmento_Rentabilidad | C30: SI(Y(margen% >= meta; ventas >= ticket alto); "Alta rentabilidad"; SI(O(margen% < piso; ventas < ticket bajo); "Revisar"; "Estandar")) | D30: Separa las operaciones que sostienen el negocio de las que hay que revisar. Usa Y para exigir las dos condiciones a la vez y O para que alcance con una sola para marcar el problema. Es la dimension de la cuarta tabla dinamica.
B31: Alerta_Logistica | C31: SI(Y(canal = "E-commerce"; costo logistico / ventas > techo); "Alerta"; "OK") | D31: Marca las ventas online cuyo costo de envio se sale del umbral operativo. Es el detalle fila a fila de lo que el KPI de costo logistico muestra agregado.
B32: Ticket | C32: SI(ventas >= ticket alto; "Alto"; SI(ventas < ticket bajo; "Bajo"; "Medio")) | D32: Clasifica el tamano de cada operacion. Permite mirar el mix de tickets sin recalcular nada.
B33: Donde estan los umbrales | C33: Parametros!C11:C14 | D33: Los cuatro cortes viven en la hoja Parametros. Cambiar un umbral reclasifica las 2.400 operaciones y actualiza las tablas dinamicas sin tocar una sola formula.
B35: COMO VIAJA UN FILTRO HASTA UN GRAFICO
B36: La cadena | C36: segmentador -> tabla dinamica -> GETPIVOTDATA (Calculos) -> grafico | D36: Los graficos no leen la tabla de hechos: leen una grilla de tamano fijo en la hoja Calculos, resuelta con GETPIVOTDATA contra las tablas dinamicas. Por eso el layout no se rompe cuando un filtro deja menos filas, y por eso los numeros del tablero y los de la hoja Tablas_Dinamicas son siempre los mismos.
B37: Un unico cache | C37: 4 segmentadores, 17 tablas dinamicas | D37: Todas las tablas dinamicas del libro comparten un solo cache de datos. Eso es lo que hace que una sola seleccion recalcule a la vez las 4 tarjetas, los 5 graficos y las 4 tablas dinamicas visibles.
B38: Por que Trimestre y no Anio | C38: El filtro de tiempo es el trimestre | D38: Un segmentador de anio dejaria sin sentido el KPI de crecimiento interanual: al elegir 2025 no habria 2024 contra que comparar. Con el trimestre, elegir Q1 compara Q1-2024 contra Q1-2025 y la comparacion se mantiene valida siempre.
B39: Si los numeros no se mueven | C39: Datos > Actualizar todo | D39: El libro pide el refresco al abrir. Algunos visores de terceros (Google Sheets, LibreOffice, la vista previa de GitHub) no ejecutan tablas dinamicas ni dibujan segmentadores: el archivo esta pensado para Excel 2010 o posterior.
B41: CRITERIOS DE DISENO DEL TABLERO
B42: Decision | C42: Que se hizo | D42: Por que
B43: Paleta | C43: Tres colores y nada mas | D43: Azul institucional (ano corriente y valor principal), gris (contexto y ano anterior) y ambar (alerta y efectos que restan). El resto son neutros de fondo y de texto. Un color que no significa nada es ruido.
B44: Interfaz | C44: Sin cuadricula ni encabezados de fila y columna | D44: El tablero tiene que leerse como un reporte, no como una planilla. Las hojas de soporte estan ocultas por la misma razon.
B45: Tarjetas de KPI | C45: Cuatro, con meta y formato condicional | D45: Cada tarjeta muestra el valor, la meta y la brecha. La que no llega a la meta pasa entera a ambar: la alerta se ve antes de leer el numero.
B46: Orden de lectura | C46: Que paso -> por que -> donde actuar | D46: Los graficos estan agrupados en tres secciones tituladas, en el orden en que un gerente hace las preguntas.
B47: Titulos de grafico | C47: Son formulas, no texto fijo | D47: Cada titulo apunta a una celda que se reescribe con los datos, asi que dice el hallazgo y no solo el nombre del grafico.
B48: Reporte ejecutivo | C48: Evidencia primero, insight despues | D48: Las tres notas del pie separan el dato cuantitativo de su significado estrategico, que es lo que permite decidir.
B49: Vocabulario | C49: Metricas de negocio, no comandos | D49: En el tablero no aparece ningun tecnicismo de software: ni nombres de funciones, ni errores de actualizacion, ni instrucciones de herramienta.
B51: ALCANCE, SUPUESTOS Y LIMITES
B52: Tema | C52: Detalle | D52: Aclaracion
B53: Origen de los datos | C53: Dataset simulado y determinista | D53: Extiende el modelo Ventas_Tech_DB del checkpoint de SQL -mismas categorias, productos y ciudades- a 24 meses, 5 regiones y 2 canales. Semilla fija: el mismo dataset se reproduce siempre igual. Todos los supuestos estan en la hoja Parametros.
B54: Ciudades imputadas | C54: Se completan por region | D54: Las ciudades que el export deja vacias se rellenan con la ciudad de referencia de la region. Es una imputacion documentada, no un dato original: la hoja Control_Calidad informa cuantas fueron.
B55: El ETL, en formulas | C55: Sin dependencias externas | D55: La limpieza esta escrita con formulas nativas de Excel a la vista, en lugar de quedar encerrada en un paso que no se puede auditar celda por celda. Se reejecuta sola al recalcular el libro y no depende de ningun conector.
B56: Formato del archivo | C56: .xlsx, sin macros | D56: El entregable se envia en .xlsx, que es un formato sin macros. Toda la interactividad del tablero -segmentadores, formato condicional, refresco al abrir, listas de validacion- es nativa y no necesita que el usuario habilite nada.
B57: Como reproducirlo | C57: generador/pipeline.py | D57: El libro se arma de cero con scripts versionados en el repositorio. El entregable es el .xlsx; los scripts existen para que el resultado sea auditable.

Sheet Calculos
A1: Capa intermedia del tablero
A2: Cadena del filtro: segmentador -> tabla dinamica -> GETPIVOTDATA (esta hoja) -> grafico.
A3: Totales por ejercicio | B3: 2024 | C3: 2025
A4: Ventas | B4: =IFERROR(GETPIVOTDATA("Ventas",Pivots_Aux!$A$3,"Anio",2024),0) -> 4726314.6 | C4: =IFERROR(GETPIVOTDATA("Ventas",Pivots_Aux!$A$3,"Anio",2025),0) -> 5566045.6
A5: Costo de producto | B5: =IFERROR(GETPIVOTDATA("CostoProd",Pivots_Aux!$J$3,"Anio",2024),0) -> 2933624.5 | C5: =IFERROR(GETPIVOTDATA("CostoProd",Pivots_Aux!$J$3,"Anio",2025),0) -> 3528561.4
A6: Costo logistico | B6: =IFERROR(GETPIVOTDATA("CostoLog",Pivots_Aux!$M$3,"Anio",2024),0) -> 102871.35 | C6: =IFERROR(GETPIVOTDATA("CostoLog",Pivots_Aux!$M$3,"Anio",2025),0) -> 183791.9
A7: Margen bruto | B7: =IFERROR(GETPIVOTDATA("Margen",Pivots_Aux!$D$3,"Anio",2024),0) -> 1689818.7 | C7: =IFERROR(GETPIVOTDATA("Margen",Pivots_Aux!$D$3,"Anio",2025),0) -> 1853692.3
A8: Unidades | B8: =IFERROR(GETPIVOTDATA("Unidades",Pivots_Aux!$G$3,"Anio",2024),0) -> 25681 | C8: =IFERROR(GETPIVOTDATA("Unidades",Pivots_Aux!$G$3,"Anio",2025),0) -> 29379
A9: Margen bruto % | B9: =IFERROR(B7/B4,0) -> 0.35753412 | C9: =IFERROR(C7/C4,0) -> 0.33303577
A10: Precio promedio por unidad | B10: =IFERROR(B4/B8,0) -> 184.03935 | C10: =IFERROR(C4/C8,0) -> 189.45661
A11: Costo de producto por unidad | B11: =IFERROR(B5/B8,0) -> 114.23327 | C11: =IFERROR(C5/C8,0) -> 120.10488
A12: Margen unitario | B12: =B10-B11 -> 69.806085 | C12: =C10-C11 -> 69.351721
A13: Costo logistico / ventas | B13: =IFERROR(B6/B4,0) -> 0.021765659 | C13: =IFERROR(C6/C4,0) -> 0.033020193
A16: KPI | B16: Valor | C16: Meta | D16: Brecha | E16: Cumple
A17: Ventas 2025 | B17: =C4 -> 5566045.6 | C17: =Parametros!$C$7 -> 5400000 | D17: =B17-C17 -> 166045.6 | E17: =IF(D17>=0,"EN META","BAJO META") -> EN META
A18: Margen bruto % | B18: =C9 -> 0.33303577 | C18: =Parametros!$C$8 -> 0.34 | D18: =B18-C18 -> -0.006964225 | E18: =IF(D18>=0,"EN META","BAJO META") -> BAJO META
A19: Crecimiento interanual | B19: =IFERROR(C4/B4-1,0) -> 0.17767141 | C19: =Parametros!$C$9 -> 0.15 | D19: =B19-C19 -> 0.027671414 | E19: =IF(D19>=0,"EN META","BAJO META") -> EN META
A20: Costo logistico / ventas | B20: =C13 -> 0.033020193 | C20: =Parametros!$C$10 -> 0.025 | D20: =C20-B20 -> -0.008020193 | E20: =IF(D20>=0,"EN META","BAJO META") -> BAJO META
A21: Variacion del margen % (p.p.) | B21: =(C9-B9)*100 -> -2.449834
A22: Variacion del costo logistico / ventas (p.p.) | B22: =(C13-B13)*100 -> 1.1254534
A27: Puente de margen bruto 2024 -> 2025 | B27: Efecto | C27: Acumulado | D27: Base | E27: Total | F27: Suma | G27: Resta
A28: Margen 2024 | B28: =B7 -> 1689818.7 | C28: =B28 -> 1689818.7 | D28: 0 | E28: =B28 -> 1689818.7 | F28: 0 | G28: 0
A29: Mas unidades | B29: =(C8-B8)*B12 -> 258142.9 | C29: =C28+B29 -> 1947961.6 | D29: =MIN(C28,C29) -> 1689818.7 | E29: 0 | F29: =MAX(B29,0) -> 258142.9 | G29: =-MIN(B29,0) -> 0
A30: Precios mas altos | B30: =(C10-B10)*C8 -> 159153.48 | C30: =C29+B30 -> 2107115.1 | D30: =MIN(C29,C30) -> 1947961.6 | E30: 0 | F30: =MAX(B30,0) -> 159153.48 | G30: =-MIN(B30,0) -> 0
A31: Costo de compra | B31: =-(C11-B11)*C8 -> -172502.23 | C31: =C30+B31 -> 1934612.9 | D31: =MIN(C30,C31) -> 1934612.9 | E31: 0 | F31: =MAX(B31,0) -> 0 | G31: =-MIN(B31,0) -> 172502.23
A32: Costo logistico | B32: =-(C6-B6) -> -80920.55 | C32: =C31+B32 -> 1853692.3 | D32: =MIN(C31,C32) -> 1853692.3 | E32: 0 | F32: =MAX(B32,0) -> 0 | G32: =-MIN(B32,0) -> 80920.55
A33: Margen 2025 | B33: =C7 -> 1853692.3 | C33: =B33 -> 1853692.3 | D33: 0 | E33: =B33 -> 1853692.3 | F33: 0 | G33: 0
A34: Control: los efectos deben cerrar en cero | B34: =ROUND(SUM(B28:B32)-B33,2) -> 0
A37: Evolucion mensual | B37: Ventas 2024 | C37: Ventas 2025 | D37: Margen % 2025 | E37: Margen 2025 | F37: Margen 2024 | G37: YTD 2024 | H37: YTD 2025 | I37: Var. mensual | J37: Mes
A38: Ene | B38: =IFERROR(GETPIVOTDATA("Ventas",Pivots_Aux!$P$3,"Periodo","2024-01"),0) -> 335709.78 | C38: =IFERROR(GETPIVOTDATA("Ventas",Pivots_Aux!$P$3,"Periodo","2025-01"),0) -> 376115.96 | D38: =IFERROR(E38/C38,0) -> 0.3184905 | E38: =IFERROR(GETPIVOTDATA("Margen",Pivots_Aux!$S$3,"Periodo","2025-01"),0) -> 119789.36 | F38: =IFERROR(GETPIVOTDATA("Margen",Pivots_Aux!$S$3,"Periodo","2024-01"),0) -> 120066.04 | G38: =SUM($B$38:B38) -> 335709.78 | H38: =SUM($C$38:C38) -> 376115.96 | I38: 0 | J38: Ene
A39: Feb | B39: =IFERROR(GETPIVOTDATA("Ventas",Pivots_Aux!$P$3,"Periodo","2024-02"),0) -> 297385.9 | C39: =IFERROR(GETPIVOTDATA("Ventas",Pivots_Aux!$P$3,"Periodo","2025-02"),0) -> 354148.74 | D39: =IFERROR(E39/C39,0) -> 0.32058482 | E39: =IFERROR(GETPIVOTDATA("Margen",Pivots_Aux!$S$3,"Periodo","2025-02"),0) -> 113534.71 | F39: =IFERROR(GETPIVOTDATA("Margen",Pivots_Aux!$S$3,"Periodo","2024-02"),0) -> 106797.24 | G39: =SUM($B$38:B39) -> 633095.68 | H39: =SUM($C$38:C39) -> 730264.7 | I39: =IFERROR(C39/C38-1,0) -> -0.058405445 | J39: Feb
A40: Mar | B40: =IFERROR(GETPIVOTDATA("Ventas",Pivots_Aux!$P$3,"Periodo","2024-03"),0) -> 362339.32 | C40: =IFERROR(GETPIVOTDATA("Ventas",Pivots_Aux!$P$3,"Periodo","2025-03"),0) -> 424353.81 | D40: =IFERROR(E40/C40,0) -> 0.31919383 | E40: =IFERROR(GETPIVOTDATA("Margen",Pivots_Aux!$S$3,"Periodo","2025-03"),0) -> 135451.12 | F40: =IFERROR(GETPIVOTDATA("Margen",Pivots_Aux!$S$3,"Periodo","2024-03"),0) -> 129799.63 | G40: =SUM($B$38:B40) -> 995435 | H40: =SUM($C$38:C40) -> 1154618.5 | I40: =IFERROR(C40/C39-1,0) -> 0.19823611 | J40: Mar
A41: Abr | B41: =IFERROR(GETPIVOTDATA("Ventas",Pivots_Aux!$P$3,"Periodo","2024-04"),0) -> 351882.72 | C41: =IFERROR(GETPIVOTDATA("Ventas",Pivots_Aux!$P$3,"Periodo","2025-04"),0) -> 401046.29 | D41: =IFERROR(E41/C41,0) -> 0.31838063 | E41: =IFERROR(GETPIVOTDATA("Margen",Pivots_Aux!$S$3,"Periodo","2025-04"),0) -> 127685.37 | F41: =IFERROR(GETPIVOTDATA("Margen",Pivots_Aux!$S$3,"Periodo","2024-04"),0) -> 126286.86 | G41: =SUM($B$38:B41) -> 1347317.7 | H41: =SUM($C$38:C41) -> 1555664.8 | I41: =IFERROR(C41/C40-1,0) -> -0.054924734 | J41: Abr
A42: May | B42: =IFERROR(GETPIVOTDATA("Ventas",Pivots_Aux!$P$3,"Periodo","2024-05"),0) -> 379787.24 | C42: =IFERROR(GETPIVOTDATA("Ventas",Pivots_Aux!$P$3,"Periodo","2025-05"),0) -> 447928.5 | D42: =IFERROR(E42/C42,0) -> 0.31447646 | E42: =IFERROR(GETPIVOTDATA("Margen",Pivots_Aux!$S$3,"Periodo","2025-05"),0) -> 140862.97 | F42: =IFERROR(GETPIVOTDATA("Margen",Pivots_Aux!$S$3,"Periodo","2024-05"),0) -> 135656.22 | G42: =SUM($B$38:B42) -> 1727105 | H42: =SUM($C$38:C42) -> 2003593.3 | I42: =IFERROR(C42/C41-1,0) -> 0.11689975 | J42: May
A43: Jun | B43: =IFERROR(GETPIVOTDATA("Ventas",Pivots_Aux!$P$3,"Periodo","2024-06"),0) -> 402575.18 | C43: =IFERROR(GETPIVOTDATA("Ventas",Pivots_Aux!$P$3,"Periodo","2025-06"),0) -> 466752.11 | D43: =IFERROR(E43/C43,0) -> 0.31764996 | E43: =IFERROR(GETPIVOTDATA("Margen",Pivots_Aux!$S$3,"Periodo","2025-06"),0) -> 148263.79 | F43: =IFERROR(GETPIVOTDATA("Margen",Pivots_Aux!$S$3,"Periodo","2024-06"),0) -> 144260.56 | G43: =SUM($B$38:B43) -> 2129680.1 | H43: =SUM($C$38:C43) -> 2470345.4 | I43: =IFERROR(C43/C42-1,0) -> 0.042023694 | J43: Jun
A44: Jul | B44: =IFERROR(GETPIVOTDATA("Ventas",Pivots_Aux!$P$3,"Periodo","2024-07"),0) -> 421091.3 | C44: =IFERROR(GETPIVOTDATA("Ventas",Pivots_Aux!$P$3,"Periodo","2025-07"),0) -> 500057.9 | D44: =IFERROR(E44/C44,0) -> 0.34359389 | E44: =IFERROR(GETPIVOTDATA("Margen",Pivots_Aux!$S$3,"Periodo","2025-07"),0) -> 171816.84 | F44: =IFERROR(GETPIVOTDATA("Margen",Pivots_Aux!$S$3,"Periodo","2024-07"),0) -> 150292.4 | G44: =SUM($B$38:B44) -> 2550771.4 | H44: =SUM($C$38:C44) -> 2970403.3 | I44: =IFERROR(C44/C43-1,0) -> 0.071356485 | J44: Jul
A45: Ago | B45: =IFERROR(GETPIVOTDATA("Ventas",Pivots_Aux!$P$3,"Periodo","2024-08"),0) -> 369456.08 | C45: =IFERROR(GETPIVOTDATA("Ventas",Pivots_Aux!$P$3,"Periodo","2025-08"),0) -> 444999.85 | D45: =IFERROR(E45/C45,0) -> 0.34508702 | E45: =IFERROR(GETPIVOTDATA("Margen",Pivots_Aux!$S$3,"Periodo","2025-08"),0) -> 153563.67 | F45: =IFERROR(GETPIVOTDATA("Margen",Pivots_Aux!$S$3,"Periodo","2024-08"),0) -> 132018.84 | G45: =SUM($B$38:B45) -> 2920227.5 | H45: =SUM($C$38:C45) -> 3415403.2 | I45: =IFERROR(C45/C44-1,0) -> -0.11010335 | J45: Ago
A46: Sep | B46: =IFERROR(GETPIVOTDATA("Ventas",Pivots_Aux!$P$3,"Periodo","2024-09"),0) -> 374810.8 | C46: =IFERROR(GETPIVOTDATA("Ventas",Pivots_Aux!$P$3,"Periodo","2025-09"),0) -> 445706.66 | D46: =IFERROR(E46/C46,0) -> 0.344371 | E46: =IFERROR(GETPIVOTDATA("Margen",Pivots_Aux!$S$3,"Periodo","2025-09"),0) -> 153488.45 | F46: =IFERROR(GETPIVOTDATA("Margen",Pivots_Aux!$S$3,"Periodo","2024-09"),0) -> 133910.29 | G46: =SUM($B$38:B46) -> 3295038.3 | H46: =SUM($C$38:C46) -> 3861109.8 | I46: =IFERROR(C46/C45-1,0) -> 0.0015883376 | J46: Sep
A47: Oct | B47: =IFERROR(GETPIVOTDATA("Ventas",Pivots_Aux!$P$3,"Periodo","2024-10"),0) -> 400237.88 | C47: =IFERROR(GETPIVOTDATA("Ventas",Pivots_Aux!$P$3,"Periodo","2025-10"),0) -> 466416.5 | D47: =IFERROR(E47/C47,0) -> 0.34605639 | E47: =IFERROR(GETPIVOTDATA("Margen",Pivots_Aux!$S$3,"Periodo","2025-10"),0) -> 161406.41 | F47: =IFERROR(GETPIVOTDATA("Margen",Pivots_Aux!$S$3,"Periodo","2024-10"),0) -> 142638.83 | G47: =SUM($B$38:B47) -> 3695276.2 | H47: =SUM($C$38:C47) -> 4327526.3 | I47: =IFERROR(C47/C46-1,0) -> 0.04646518 | J47: Oct
A48: Nov | B48: =IFERROR(GETPIVOTDATA("Ventas",Pivots_Aux!$P$3,"Periodo","2024-11"),0) -> 474654.18 | C48: =IFERROR(GETPIVOTDATA("Ventas",Pivots_Aux!$P$3,"Periodo","2025-11"),0) -> 567804.81 | D48: =IFERROR(E48/C48,0) -> 0.34586562 | E48: =IFERROR(GETPIVOTDATA("Margen",Pivots_Aux!$S$3,"Periodo","2025-11"),0) -> 196384.16 | F48: =IFERROR(GETPIVOTDATA("Margen",Pivots_Aux!$S$3,"Periodo","2024-11"),0) -> 169645.33 | G48: =SUM($B$38:B48) -> 4169930.4 | H48: =SUM($C$38:C48) -> 4895331.1 | I48: =IFERROR(C48/C47-1,0) -> 0.21737719 | J48: Nov
A49: Dic | B49: =IFERROR(GETPIVOTDATA("Ventas",Pivots_Aux!$P$3,"Periodo","2024-12"),0) -> 556384.22 | C49: =IFERROR(GETPIVOTDATA("Ventas",Pivots_Aux!$P$3,"Periodo","2025-12"),0) -> 670714.47 | D49: =IFERROR(E49/C49,0) -> 0.34507301 | E49: =IFERROR(GETPIVOTDATA("Margen",Pivots_Aux!$S$3,"Periodo","2025-12"),0) -> 231445.46 | F49: =IFERROR(GETPIVOTDATA("Margen",Pivots_Aux!$S$3,"Periodo","2024-12"),0) -> 198446.47 | G49: =SUM($B$38:B49) -> 4726314.6 | H49: =SUM($C$38:C49) -> 5566045.6 | I49: =IFERROR(C49/C48-1,0) -> 0.18124126 | J49: Dic
A53: Margen % por categoria | B53: Margen % 2024 | C53: Margen % 2025 | D53: Ventas 2025
A54: Computacion | B54: =IFERROR((IFERROR(GETPIVOTDATA("Margen",Pivots_Aux!$Y$3,"Cat_Anio","Computacion 2024"),0))/(IFERROR(GETPIVOTDATA("Ventas",Pivots_Aux!$V$3,"Cat_Anio","Computacion 2024"),0)),0) -> 0.31763326 | C54: =IFERROR((IFERROR(GETPIVOTDATA("Margen",Pivots_Aux!$Y$3,"Cat_Anio","Computacion 2025"),0))/(IFERROR(GETPIVOTDATA("Ventas",Pivots_Aux!$V$3,"Cat_Anio","Computacion 2025"),0)),0) -> 0.28973779 | D54: =IFERROR(GETPIVOTDATA("Ventas",Pivots_Aux!$V$3,"Cat_Anio","Computacion 2025"),0) -> 3629530.2
A55: Accesorios | B55: =IFERROR((IFERROR(GETPIVOTDATA("Margen",Pivots_Aux!$Y$3,"Cat_Anio","Accesorios 2024"),0))/(IFERROR(GETPIVOTDATA("Ventas",Pivots_Aux!$V$3,"Cat_Anio","Accesorios 2024"),0)),0) -> 0.45265887 | C55: =IFERROR((IFERROR(GETPIVOTDATA("Margen",Pivots_Aux!$Y$3,"Cat_Anio","Accesorios 2025"),0))/(IFERROR(GETPIVOTDATA("Ventas",Pivots_Aux!$V$3,"Cat_Anio","Accesorios 2025"),0)),0) -> 0.43574494 | D55: =IFERROR(GETPIVOTDATA("Ventas",Pivots_Aux!$V$3,"Cat_Anio","Accesorios 2025"),0) -> 963729.38
A56: Audio | B56: =IFERROR((IFERROR(GETPIVOTDATA("Margen",Pivots_Aux!$Y$3,"Cat_Anio","Audio 2024"),0))/(IFERROR(GETPIVOTDATA("Ventas",Pivots_Aux!$V$3,"Cat_Anio","Audio 2024"),0)),0) -> 0.42234673 | C56: =IFERROR((IFERROR(GETPIVOTDATA("Margen",Pivots_Aux!$Y$3,"Cat_Anio","Audio 2025"),0))/(IFERROR(GETPIVOTDATA("Ventas",Pivots_Aux!$V$3,"Cat_Anio","Audio 2025"),0)),0) -> 0.40552977 | D56: =IFERROR(GETPIVOTDATA("Ventas",Pivots_Aux!$V$3,"Cat_Anio","Audio 2025"),0) -> 480609.25
A57: Almacenamiento | B57: =IFERROR((IFERROR(GETPIVOTDATA("Margen",Pivots_Aux!$Y$3,"Cat_Anio","Almacenamiento 2024"),0))/(IFERROR(GETPIVOTDATA("Ventas",Pivots_Aux!$V$3,"Cat_Anio","Almacenamiento 2024"),0)),0) -> 0.3975592 | C57: =IFERROR((IFERROR(GETPIVOTDATA("Margen",Pivots_Aux!$Y$3,"Cat_Anio","Almacenamiento 2025"),0))/(IFERROR(GETPIVOTDATA("Ventas",Pivots_Aux!$V$3,"Cat_Anio","Almacenamiento 2025"),0)),0) -> 0.38042972 | D57: =IFERROR(GETPIVOTDATA("Ventas",Pivots_Aux!$V$3,"Cat_Anio","Almacenamiento 2025"),0) -> 492176.82
A61: Productos 2025 | B61: Ventas 2025 | C61: Crecimiento | D61: Margen % | E61: X en meta | F61: Y en meta | G61: X riesgo | H61: Y riesgo
A62: Laptop Pro 15 | B62: =IFERROR(GETPIVOTDATA("Ventas",Pivots_Aux!$AB$3,"Prod_Anio","Laptop Pro 15 2025"),0) -> 1313626.1 | C62: =IFERROR((IFERROR(GETPIVOTDATA("Ventas",Pivots_Aux!$AB$3,"Prod_Anio","Laptop Pro 15 2025"),0))/(IFERROR(GETPIVOTDATA("Ventas",Pivots_Aux!$AB$3,"Prod_Anio","Laptop Pro 15 2024"),0))-1,0) -> 0.15276474 | D62: =IFERROR((IFERROR(GETPIVOTDATA("Margen",Pivots_Aux!$AE$3,"Prod_Anio","Laptop Pro 15 2025"),0))/(IFERROR(GETPIVOTDATA("Ventas",Pivots_Aux!$AB$3,"Prod_Anio","Laptop Pro 15 2025"),0)),0) -> 0.31914457 | G62: =C62 -> 0.15276474 | H62: =D62 -> 0.31914457
A63: Monitor 4K 27 | B63: =IFERROR(GETPIVOTDATA("Ventas",Pivots_Aux!$AB$3,"Prod_Anio","Monitor 4K 27 2025"),0) -> 498411.2 | C63: =IFERROR((IFERROR(GETPIVOTDATA("Ventas",Pivots_Aux!$AB$3,"Prod_Anio","Monitor 4K 27 2025"),0))/(IFERROR(GETPIVOTDATA("Ventas",Pivots_Aux!$AB$3,"Prod_Anio","Monitor 4K 27 2024"),0))-1,0) -> 0.17605008 | D63: =IFERROR((IFERROR(GETPIVOTDATA("Margen",Pivots_Aux!$AE$3,"Prod_Anio","Monitor 4K 27 2025"),0))/(IFERROR(GETPIVOTDATA("Ventas",Pivots_Aux!$AB$3,"Prod_Anio","Monitor 4K 27 2025"),0)),0) -> 0.33418581 | E63: =C63 -> 0.17605008 | F63: =D63 -> 0.33418581
A64: PC Gamer Ryzen | B64: =IFERROR(GETPIVOTDATA("Ventas",Pivots_Aux!$AB$3,"Prod_Anio","PC Gamer Ryzen 2025"),0) -> 1817492.8 | C64: =IFERROR((IFERROR(GETPIVOTDATA("Ventas",Pivots_Aux!$AB$3,"Prod_Anio","PC Gamer Ryzen 2025"),0))/(IFERROR(GETPIVOTDATA("Ventas",Pivots_Aux!$AB$3,"Prod_Anio","PC Gamer Ryzen 2024"),0))-1,0) -> 0.20859205 | D64: =IFERROR((IFERROR(GETPIVOTDATA("Margen",Pivots_Aux!$AE$3,"Prod_Anio","PC Gamer Ryzen 2025"),0))/(IFERROR(GETPIVOTDATA("Ventas",Pivots_Aux!$AB$3,"Prod_Anio","PC Gamer Ryzen 2025"),0)),0) -> 0.25629453 | G64: =C64 -> 0.20859205 | H64: =D64 -> 0.25629453
A65: Mouse Inalambrico | B65: =IFERROR(GETPIVOTDATA("Ventas",Pivots_Aux!$AB$3,"Prod_Anio","Mouse Inalambrico 2025"),0) -> 142604.16 | C65: =IFERROR((IFERROR(GETPIVOTDATA("Ventas",Pivots_Aux!$AB$3,"Prod_Anio","Mouse Inalambrico 2025"),0))/(IFERROR(GETPIVOTDATA("Ventas",Pivots_Aux!$AB$3,"Prod_Anio","Mouse Inalambrico 2024"),0))-1,0) -> 0.15103978 | D65: =IFERROR((IFERROR(GETPIVOTDATA("Margen",Pivots_Aux!$AE$3,"Prod_Anio","Mouse Inalambrico 2025"),0))/(IFERROR(GETPIVOTDATA("Ventas",Pivots_Aux!$AB$3,"Prod_Anio","Mouse Inalambrico 2025"),0)),0) -> 0.47244519 | E65: =C65 -> 0.15103978 | F65: =D65 -> 0.47244519
A66: Teclado Mecanico | B66: =IFERROR(GETPIVOTDATA("Ventas",Pivots_Aux!$AB$3,"Prod_Anio","Teclado Mecanico 2025"),0) -> 490311.2 | C66: =IFERROR((IFERROR(GETPIVOTDATA("Ventas",Pivots_Aux!$AB$3,"Prod_Anio","Teclado Mecanico 2025"),0))/(IFERROR(GETPIVOTDATA("Ventas",Pivots_Aux!$AB$3,"Prod_Anio","Teclado Mecanico 2024"),0))-1,0) -> 0.16515499 | D66: =IFERROR((IFERROR(GETPIVOTDATA("Margen",Pivots_Aux!$AE$3,"Prod_Anio","Teclado Mecanico 2025"),0))/(IFERROR(GETPIVOTDATA("Ventas",Pivots_Aux!$AB$3,"Prod_Anio","Teclado Mecanico 2025"),0)),0) -> 0.44595532 | E66: =C66 -> 0.16515499 | F66: =D66 -> 0.44595532
A67: Webcam Full HD | B67: =IFERROR(GETPIVOTDATA("Ventas",Pivots_Aux!$AB$3,"Prod_Anio","Webcam Full HD 2025"),0) -> 330814.02 | C67: =IFERROR((IFERROR(GETPIVOTDATA("Ventas",Pivots_Aux!$AB$3,"Prod_Anio","Webcam Full HD 2025"),0))/(IFERROR(GETPIVOTDATA("Ventas",Pivots_Aux!$AB$3,"Prod_Anio","Webcam Full HD 2024"),0))-1,0) -> 0.14113661 | D67: =IFERROR((IFERROR(GETPIVOTDATA("Margen",Pivots_Aux!$AE$3,"Prod_Anio","Webcam Full HD 2025"),0))/(IFERROR(GETPIVOTDATA("Ventas",Pivots_Aux!$AB$3,"Prod_Anio","Webcam Full HD 2025"),0)),0) -> 0.40479137 | E67: =C67 -> 0.14113661 | F67: =D67 -> 0.40479137
A68: Auriculares BT Pro | B68: =IFERROR(GETPIVOTDATA("Ventas",Pivots_Aux!$AB$3,"Prod_Anio","Auriculares BT Pro 2025"),0) -> 282858.21 | C68: =IFERROR((IFERROR(GETPIVOTDATA("Ventas",Pivots_Aux!$AB$3,"Prod_Anio","Auriculares BT Pro 2025"),0))/(IFERROR(GETPIVOTDATA("Ventas",Pivots_Aux!$AB$3,"Prod_Anio","Auriculares BT Pro 2024"),0))-1,0) -> 0.21049667 | D68: =IFERROR((IFERROR(GETPIVOTDATA("Margen",Pivots_Aux!$AE$3,"Prod_Anio","Auriculares BT Pro 2025"),0))/(IFERROR(GETPIVOTDATA("Ventas",Pivots_Aux!$AB$3,"Prod_Anio","Auriculares BT Pro 2025"),0)),0) -> 0.42063775 | E68: =C68 -> 0.21049667 | F68: =D68 -> 0.42063775
A69: Parlante Bluetooth | B69: =IFERROR(GETPIVOTDATA("Ventas",Pivots_Aux!$AB$3,"Prod_Anio","Parlante Bluetooth 2025"),0) -> 197751.04 | C69: =IFERROR((IFERROR(GETPIVOTDATA("Ventas",Pivots_Aux!$AB$3,"Prod_Anio","Parlante Bluetooth 2025"),0))/(IFERROR(GETPIVOTDATA("Ventas",Pivots_Aux!$AB$3,"Prod_Anio","Parlante Bluetooth 2024"),0))-1,0) -> 0.16828842 | D69: =IFERROR((IFERROR(GETPIVOTDATA("Margen",Pivots_Aux!$AE$3,"Prod_Anio","Parlante Bluetooth 2025"),0))/(IFERROR(GETPIVOTDATA("Ventas",Pivots_Aux!$AB$3,"Prod_Anio","Parlante Bluetooth 2025"),0)),0) -> 0.3839197 | E69: =C69 -> 0.16828842 | F69: =D69 -> 0.3839197
A70: SSD Externo 1TB | B70: =IFERROR(GETPIVOTDATA("Ventas",Pivots_Aux!$AB$3,"Prod_Anio","SSD Externo 1TB 2025"),0) -> 387109.46 | C70: =IFERROR((IFERROR(GETPIVOTDATA("Ventas",Pivots_Aux!$AB$3,"Prod_Anio","SSD Externo 1TB 2025"),0))/(IFERROR(GETPIVOTDATA("Ventas",Pivots_Aux!$AB$3,"Prod_Anio","SSD Externo 1TB 2024"),0))-1,0) -> 0.16552965 | D70: =IFERROR((IFERROR(GETPIVOTDATA("Margen",Pivots_Aux!$AE$3,"Prod_Anio","SSD Externo 1TB 2025"),0))/(IFERROR(GETPIVOTDATA("Ventas",Pivots_Aux!$AB$3,"Prod_Anio","SSD Externo 1TB 2025"),0)),0) -> 0.36393089 | E70: =C70 -> 0.16552965 | F70: =D70 -> 0.36393089
A71: Pendrive 256GB | B71: =IFERROR(GETPIVOTDATA("Ventas",Pivots_Aux!$AB$3,"Prod_Anio","Pendrive 256GB 2025"),0) -> 105067.36 | C71: =IFERROR((IFERROR(GETPIVOTDATA("Ventas",Pivots_Aux!$AB$3,"Prod_Anio","Pendrive 256GB 2025"),0))/(IFERROR(GETPIVOTDATA("Ventas",Pivots_Aux!$AB$3,"Prod_Anio","Pendrive 256GB 2024"),0))-1,0) -> 0.17408522 | D71: =IFERROR((IFERROR(GETPIVOTDATA("Margen",Pivots_Aux!$AE$3,"Prod_Anio","Pendrive 256GB 2025"),0))/(IFERROR(GETPIVOTDATA("Ventas",Pivots_Aux!$AB$3,"Prod_Anio","Pendrive 256GB 2025"),0)),0) -> 0.4412179 | E71: =C71 -> 0.17408522 | F71: =D71 -> 0.4412179
A75: Regiones | B75: Ventas | C75: Margen | D75: Margen %
A76: AMBA | B76: =IFERROR(GETPIVOTDATA("Ventas",Pivots_Aux!$AH$3,"Region","AMBA"),0) -> 3896685.1 | C76: =IFERROR(GETPIVOTDATA("Margen",Pivots_Aux!$AK$3,"Region","AMBA"),0) -> 1341318.3 | D76: =IFERROR(C76/B76,0) -> 0.34422036
A77: Centro | B77: =IFERROR(GETPIVOTDATA("Ventas",Pivots_Aux!$AH$3,"Region","Centro"),0) -> 2262766.3 | C77: =IFERROR(GETPIVOTDATA("Margen",Pivots_Aux!$AK$3,"Region","Centro"),0) -> 780708.6 | D77: =IFERROR(C77/B77,0) -> 0.34502397
A78: Litoral | B78: =IFERROR(GETPIVOTDATA("Ventas",Pivots_Aux!$AH$3,"Region","Litoral"),0) -> 1655093.7 | C78: =IFERROR(GETPIVOTDATA("Margen",Pivots_Aux!$AK$3,"Region","Litoral"),0) -> 569389.84 | D78: =IFERROR(C78/B78,0) -> 0.34402272
A79: Cuyo | B79: =IFERROR(GETPIVOTDATA("Ventas",Pivots_Aux!$AH$3,"Region","Cuyo"),0) -> 1247848.4 | C79: =IFERROR(GETPIVOTDATA("Margen",Pivots_Aux!$AK$3,"Region","Cuyo"),0) -> 427843.83 | D79: =IFERROR(C79/B79,0) -> 0.34286523
A80: NOA | B80: =IFERROR(GETPIVOTDATA("Ventas",Pivots_Aux!$AH$3,"Region","NOA"),0) -> 1229966.7 | C80: =IFERROR(GETPIVOTDATA("Margen",Pivots_Aux!$AK$3,"Region","NOA"),0) -> 424250.41 | D80: =IFERROR(C80/B80,0) -> 0.34492837
A81: Region lider por ventas | B81: =INDEX($A$76:$A$80,MATCH(MAX($B$76:$B$80),$B$76:$B$80,0)) -> AMBA
A82: Participacion de la region lider | B82: =IFERROR(MAX($B$76:$B$80)/SUM($B$76:$B$80),0) -> 0.37859976
A84: Textos que el tablero muestra
A85: titular | B85: ="Las ventas crecen "&TEXT(B19,"0.0%")&" y el margen cae "&TEXT(ABS(B21),"0.0")&" p.p.: el costo de compra y la logistica del e-commerce se reparten el deterioro" -> Las ventas crecen 17.8% y el margen cae 2.4 p.p.: el costo de compra y la logistica del e-commerce se reparten el deterioro
A86: bajada | B86: ="El margen bruto pasa de "&TEXT(B9,"0.0%")&" a "&TEXT(C9,"0.0%")&". La logistica explica "&TEXT(IFERROR(ABS(B32)/(ABS(B31)+ABS(B32)),0),"0%")&" del mayor costo y el resto es precio de compra: son dos causas, no una." -> El margen bruto pasa de 35.8% a 33.3%. La logistica explica 32% del mayor costo y el resto es precio de compra: son dos causas, no una.
A87: g1 | B87: ="El margen se recupera en el segundo semestre ("&TEXT(IFERROR(SUM(E44:E49)/SUM(C44:C49),0),"0.0%")&") pero no vuelve al nivel de 2024 ("&TEXT(IFERROR(SUM(F44:F49)/SUM(B44:B49),0),"0.0%")&")" -> El margen se recupera en el segundo semestre (34.5%) pero no vuelve al nivel de 2024 (35.7%)
A88: g2 | B88: ="El acumulado del ano cierra "&TEXT(IFERROR(H49/G49-1,0),"0.0%")&" arriba de 2024, y la brecha se abre desde el primer trimestre" -> El acumulado del ano cierra 17.8% arriba de 2024, y la brecha se abre desde el primer trimestre
A89: g3 | B89: ="Volumen y precio sumaron "&TEXT(B29+B30,"$#,##0")&" de margen; los costos se llevaron "&TEXT(ABS(B31)+ABS(B32),"$#,##0") -> Volumen y precio sumaron $417,296 de margen; los costos se llevaron $253,423
A90: g4 | B90: ="Computacion concentra la caida: pierde "&TEXT(ABS((C54-B54)*100),"0.0")&" p.p. de margen" -> Computacion concentra la caida: pierde 2.8 p.p. de margen
A91: g5 | B91: ="Los productos que mas crecen son los que menos margen dejan" -> Los productos que mas crecen son los que menos margen dejan
A92: nota1 | B92: ="EVIDENCIA: las ventas suben "&TEXT(B19,"0.0%")&" y las unidades "&TEXT(IFERROR(C8/B8-1,0),"0.0%")&". INSIGHT: el crecimiento es de volumen, no de precio, asi que la demanda es real y conviene sostener el plan comercial." -> EVIDENCIA: las ventas suben 17.8% y las unidades 14.4%. INSIGHT: el crecimiento es de volumen, no de precio, asi que la demanda es real y conviene sostener el plan comercial.
A93: nota2 | B93: ="EVIDENCIA: el costo de compra resta "&TEXT(ABS(B31),"$#,##0")&" y la logistica "&TEXT(ABS(B32),"$#,##0")&" de margen. INSIGHT: la caida tiene dos causas, no una; atribuirla solo al e-commerce sobreestima su peso y desviaria el presupuesto de correccion." -> EVIDENCIA: el costo de compra resta $172,502 y la logistica $80,921 de margen. INSIGHT: la caida tiene dos causas, no una; atribuirla solo al e-commerce sobreestima su peso y desviaria el presupuesto de correccion.
A94: nota3 | B94: ="EVIDENCIA: el segundo semestre ("&TEXT(IFERROR(SUM(E44:E49)/SUM(C44:C49),0),"0.0%")&") supera al primero ("&TEXT(IFERROR(SUM(E38:E43)/SUM(C38:C43),0),"0.0%")&") pero sigue por debajo del mismo periodo de 2024 ("&TEXT(IFERROR(SUM(F44:F49)/SUM(B44:B49),0),"0.0%")&"). INSIGHT: la correccion del Q3 funciona pero es parcial; hay que sostenerla en el proximo semestre antes de fijar nuevas metas." -> EVIDENCIA: el segundo semestre (34.5%) supera al primero (31.8%) pero sigue por debajo del mismo periodo de 2024 (35.7%). INSIGHT: la correccion del Q3 funciona pero es parcial; hay que sostenerla en el proximo semestre antes de fijar nuevas metas.
A95: pie5 | B95: =IF(LEN(C95)=0,"Todos los productos quedan por encima del corte de margen.","Zona de riesgo (margen por debajo de "&TEXT(Parametros!$C$15,"0%")&"): "&LEFT(C95,LEN(C95)-2)&". El resto de los productos esta en meta.") -> Zona de riesgo (margen por debajo de 33%): Laptop Pro 15, PC Gamer Ryzen. El resto de los productos esta en meta. | C95: =IF(D62<Parametros!$C$15,A62&", ","")&IF(D63<Parametros!$C$15,A63&", ","")&IF(D64<Parametros!$C$15,A64&", ","")&IF(D65<Parametros!$C$15,A65&", ","")&IF(D66<Parametros!$C$15,A66&", ","")&IF(D67<Parametros!$C$15,A67&", ","")&IF(D68<Parametros!$C$15,A68&", ","")&IF(D69<Parametros!$C$15,A69&", ","")&IF(D70<Parametros!$C$15,A70&", ","")&IF(D71<Parametros!$C$15,A71&", ","") -> Laptop Pro 15, PC Gamer Ryzen,

Sheet Pivots_Aux
A1: Tablas dinamicas de soporte. Los graficos del tablero las leen con GETPIVOTDATA sobre una grilla de tamano fijo. Se ocultan porque son infraestructura, no lectura. No editar a mano.
A3: Anio | B3: Ventas | D3: Anio | E3: Margen | G3: Anio | H3: Unidades | J3: Anio | K3: CostoProd | M3: Anio | N3: CostoLog | P3: Periodo | Q3: Ventas | S3: Periodo | T3: Margen | V3: Cat_Anio | W3: Ventas | Y3: Cat_Anio | Z3: Margen | AB3: Prod_Anio | AC3: Ventas | AE3: Prod_Anio | AF3: Margen | AH3: Region | AI3: Ventas | AK3: Region | AL3: Margen
A4: 2024 | B4: 4726314.6 | D4: 2024 | E4: 1689818.7 | G4: 2024 | H4: 25681 | J4: 2024 | K4: 2933624.5 | M4: 2024 | N4: 102871.35 | P4: 2024-01 | Q4: 335709.78 | S4: 2024-01 | T4: 120066.04 | V4: Computacion 2024 | W4: 3067155 | Y4: Computacion 2024 | Z4: 974230.43 | AB4: Laptop Pro 15 2024 | AC4: 1139544 | AE4: Laptop Pro 15 2024 | AF4: 393830.85 | AH4: AMBA | AI4: 3896685.1 | AK4: AMBA | AL4: 1341318.3
A5: 2025 | B5: 5566045.6 | D5: 2025 | E5: 1853692.3 | G5: 2025 | H5: 29379 | J5: 2025 | K5: 3528561.4 | M5: 2025 | N5: 183791.9 | P5: 2024-02 | Q5: 297385.9 | S5: 2024-02 | T5: 106797.24 | V5: Accesorios 2024 | W5: 834602.3 | Y5: Accesorios 2024 | Z5: 377790.13 | AB5: Monitor 4K 27 2024 | AC5: 423801 | AE5: Monitor 4K 27 2024 | AF5: 153039.62 | AH5: Centro | AI5: 2262766.3 | AK5: Centro | AL5: 780708.6
A6: Total Result | B6: 10292360 | D6: Total Result | E6: 3543511 | G6: Total Result | H6: 55060 | J6: Total Result | K6: 6462185.9 | M6: Total Result | N6: 286663.25 | P6: 2024-03 | Q6: 362339.32 | S6: 2024-03 | T6: 129799.63 | V6: Audio 2024 | W6: 402936.8 | Y6: Audio 2024 | Z6: 170179.04 | AB6: PC Gamer Ryzen 2024 | AC6: 1503810 | AE6: PC Gamer Ryzen 2024 | AF6: 427359.96 | AH6: Litoral | AI6: 1655093.7 | AK6: Litoral | AL6: 569389.84
P7: 2024-04 | Q7: 351882.72 | S7: 2024-04 | T7: 126286.86 | V7: Almacenamiento 2024 | W7: 421620.5 | Y7: Almacenamiento 2024 | Z7: 167619.11 | AB7: Mouse Inalambrico 2024 | AC7: 123891.6 | AE7: Mouse Inalambrico 2024 | AF7: 60540.18 | AH7: Cuyo | AI7: 1247848.4 | AK7: Cuyo | AL7: 427843.83
P8: 2024-05 | Q8: 379787.24 | S8: 2024-05 | T8: 135656.22 | V8: Computacion 2025 | W8: 3629530.2 | Y8: Computacion 2025 | Z8: 1051612.1 | AB8: Teclado Mecanico 2024 | AC8: 420812 | AE8: Teclado Mecanico 2024 | AF8: 194829.25 | AH8: NOA | AI8: 1229966.7 | AK8: NOA | AL8: 424250.41
P9: 2024-06 | Q9: 402575.18 | S9: 2024-06 | T9: 144260.56 | V9: Accesorios 2025 | W9: 963729.38 | Y9: Accesorios 2025 | Z9: 419940.2 | AB9: Webcam Full HD 2024 | AC9: 289898.7 | AE9: Webcam Full HD 2024 | AF9: 122420.7 | AH9: Total Result | AI9: 10292360 | AK9: Total Result | AL9: 3543511
P10: 2024-07 | Q10: 421091.3 | S10: 2024-07 | T10: 150292.4 | V10: Audio 2025 | W10: 480609.25 | Y10: Audio 2025 | Z10: 194901.36 | AB10: Auriculares BT Pro 2024 | AC10: 233671.2 | AE10: Auriculares BT Pro 2024 | AF10: 102216.65
P11: 2024-08 | Q11: 369456.08 | S11: 2024-08 | T11: 132018.84 | V11: Almacenamiento 2025 | W11: 492176.82 | Y11: Almacenamiento 2025 | Z11: 187238.69 | AB11: Parlante Bluetooth 2024 | AC11: 169265.6 | AE11: Parlante Bluetooth 2024 | AF11: 67962.39
P12: 2024-09 | Q12: 374810.8 | S12: 2024-09 | T12: 133910.29 | V12: Total Result | W12: 10292360 | Y12: Total Result | Z12: 3543511 | AB12: SSD Externo 1TB 2024 | AC12: 332131.8 | AE12: SSD Externo 1TB 2024 | AF12: 126653.78
P13: 2024-10 | Q13: 400237.88 | S13: 2024-10 | T13: 142638.83 | AB13: Pendrive 256GB 2024 | AC13: 89488.7 | AE13: Pendrive 256GB 2024 | AF13: 40965.33
P14: 2024-11 | Q14: 474654.18 | S14: 2024-11 | T14: 169645.33 | AB14: Laptop Pro 15 2025 | AC14: 1313626.1 | AE14: Laptop Pro 15 2025 | AF14: 419236.65
P15: 2024-12 | Q15: 556384.22 | S15: 2024-12 | T15: 198446.47 | AB15: Monitor 4K 27 2025 | AC15: 498411.2 | AE15: Monitor 4K 27 2025 | AF15: 166561.95
P16: 2025-01 | Q16: 376115.96 | S16: 2025-01 | T16: 119789.36 | AB16: PC Gamer Ryzen 2025 | AC16: 1817492.8 | AE16: PC Gamer Ryzen 2025 | AF16: 465813.46
P17: 2025-02 | Q17: 354148.74 | S17: 2025-02 | T17: 113534.71 | AB17: Mouse Inalambrico 2025 | AC17: 142604.16 | AE17: Mouse Inalambrico 2025 | AF17: 67372.65
P18: 2025-03 | Q18: 424353.81 | S18: 2025-03 | T18: 135451.12 | AB18: Teclado Mecanico 2025 | AC18: 490311.2 | AE18: Teclado Mecanico 2025 | AF18: 218656.89
P19: 2025-04 | Q19: 401046.29 | S19: 2025-04 | T19: 127685.37 | AB19: Webcam Full HD 2025 | AC19: 330814.02 | AE19: Webcam Full HD 2025 | AF19: 133910.66
P20: 2025-05 | Q20: 447928.5 | S20: 2025-05 | T20: 140862.97 | AB20: Auriculares BT Pro 2025 | AC20: 282858.21 | AE20: Auriculares BT Pro 2025 | AF20: 118980.84
P21: 2025-06 | Q21: 466752.11 | S21: 2025-06 | T21: 148263.79 | AB21: Parlante Bluetooth 2025 | AC21: 197751.04 | AE21: Parlante Bluetooth 2025 | AF21: 75920.52
P22: 2025-07 | Q22: 500057.9 | S22: 2025-07 | T22: 171816.84 | AB22: SSD Externo 1TB 2025 | AC22: 387109.46 | AE22: SSD Externo 1TB 2025 | AF22: 140881.09
P23: 2025-08 | Q23: 444999.85 | S23: 2025-08 | T23: 153563.67 | AB23: Pendrive 256GB 2025 | AC23: 105067.36 | AE23: Pendrive 256GB 2025 | AF23: 46357.6
P24: 2025-09 | Q24: 445706.66 | S24: 2025-09 | T24: 153488.45 | AB24: Total Result | AC24: 10292360 | AE24: Total Result | AF24: 3543511
P25: 2025-10 | Q25: 466416.5 | S25: 2025-10 | T25: 161406.41
P26: 2025-11 | Q26: 567804.81 | S26: 2025-11 | T26: 196384.16
P27: 2025-12 | Q27: 670714.47 | S27: 2025-12 | T27: 231445.46
P28: Total Result | Q28: 10292360 | S28: Total Result | T28: 3543511
